Workbook
Name \: "april 2003+Sheet1!$1:$540"
Name \\100: #REF!
Name \\117: #REF!
Name \\122: #REF!
Name \\159: #REF!
Name \\164: #REF!
Name \\165: #REF!
Name \\166: #REF!
Name \\167: #REF!
Name \\168: #REF!
Name \\169: #REF!
Name \\170: #REF!
Name \\295: #REF!
Name \\297: #REF!
Name \\426: #REF!
Name \\427: #REF!
Name \\428: #REF!
Name \\499: #REF!
Name \\500: #REF!
Name \\501: #REF!
Name \\502: #REF!
Name \\505: #REF!
Name \\507: #REF!
Name \\510: #REF!
Name \\512: #REF!
Name \\514: #REF!
Name \\533: #REF!
Name \\542: #REF!
Name \\544: #REF!
Name \\546: #REF!
Name \\549: #REF!
Name \\550: #REF!
Name \\551: #REF!
Name \\552: #REF!
Name \\554: #REF!
Name \\560: #REF!
Name \\575: #REF!
Name \\576: #REF!
Name \\579: #REF!
Name \\580: #REF!
Name \\582: #REF!
Name \\590: #REF!
Name \\oob: #REF!
Name \0: #REF!
Name \0.001: #REF!
Name \000: #REF!
Name \000538: #REF!
Name \01?299: #REF!
Name \0100: #REF!
Name \0101: #REF!
Name \0102: #REF!
Name \0103: #REF!
Name \0104: #REF!
Name \0105: #REF!
Name \0106: #REF!
Name \0107: #REF!
Name \0110: #REF!
Name \0111: #REF!
Name \0113: #REF!
Name \0114: #REF!

Sheet Meeting Summary
A1: COSTING SHEET ALIGNMENT – MEETING SUMMARY (21.04.2026)
A2: Mozambique Commodity Exports
A4: 1. MEETING OBJECTIVE
A5: Goal | B5: Align on a standardised forward-looking costing sheet to support buy/no-buy decisions, margin analysis, and performance tracking for commodity exports from Mozambique.
A6: Immediate Priority | B6: Soybeans and Mung Beans – harvest has already started.
A7: Target | B7: Establish ONE source of truth for costs, aligned across procurement, operations and finance.
A9: 2. CURRENT SITUATION & GAPS
A10: Existing Sheets | B10: Costing sheets exist only for actual shipments (vessel-based: pigeon peas & cashew). Not sufficient for forward-looking purchasing decisions.
A11: Gap | B11: No current forward-looking template that procurement can use daily.
A12: Problem | B12: Cost elements exist but are NOT consolidated into a single decision-making tool.
A14: 3. PURPOSE OF THE COSTING SHEET
A15: Calculate | B15: Total FOB cost before purchasing.
A16: Decide | B16: Whether to buy or not buy commodities based on expected profitability.
A17: Track | B17: Performance during the season.
A18: Report | B18: Support monthly management P&L reporting and financial performance tracking.
A20: 4. COSTING SHEET DESIGN – KEY PRINCIPLES
A21: Structure | B21: Differ by commodity (soybean, mung beans, sesame, pigeon peas, cashew, peanuts).
A22: Buying Models | B22: Allow for multiple buying models – e.g. delivered to port vs. up-country (separate columns within same sheet).
A23: Cost Types | B23: Include both variable and fixed costs.
A24: Inputs | B24: Procurement inputs daily purchase prices; operational & fixed costs pre-defined and updated periodically.
A26: 5. COMMODITIES – PRIORITIES
A27: URGENT | B27: Soybeans, Mung Beans (harvest already started).
A28: Subsequent | B28: Sesame, Pigeon Peas, Cashew.
A29: Also started | B29: Peanut – to follow same approach once soybean/mung bean sheets are finalised.
A31: 6. PORT LOCATION & TEMPLATES
A32: Ports | B32: Soybeans and Mung Beans delivered primarily Nacala, potentially Beira.
A33: Decision | B33: Separate costing templates for NACALA and BEIRA (same cost components, different rates).
A35: 7. ROLES & RESPONSIBILITIES
A36: David Martins | B36: Overall responsibility for costing.
A37: Elina Chiluvane | B37: Day-to-day detailed costing work.
A38: Manoj Saini | B38: Procurement inputs: purchase prices and buying assumptions.
A39: Osama Burhan | B39: Operations oversight – assigns Sidahmed to provide operational cost inputs.
A40: Sidahmed | B40: Provide operational cost inputs to Elina.
A42: 8. WAREHOUSE COST ALLOCATION
A43: Warehouses | B43: Seasonal; not shared simultaneously by multiple commodities but reused across seasons.
A44: Fully Assigned | B44: If fully assigned to export – full cost belongs to that export commodity.
A45: Underutilised | B45: Underutilisation treated as overhead, NOT allocated to product.
A46: Forward-looking | B46: Allocate based on planned volumes and expected utilisation.
A47: Actuals | B47: Allocation adjusted monthly based on actual utilisation.
A48: Ops to provide | B48: Warehouse capacity, allocation plans, monthly utilisation.
A50: 9. METHODOLOGY ALIGNMENT
A51: Aligned with | B51: Existing Invictus-based vessel costing methodology.
A52: Reference sheets | B52: Existing pigeon pea and cashew costing sheets – shared for reference and structural base (numbers not copied).
A54: 10. MACHINES INSTALLATION – OPERATIONAL URGENCY
A55: Status | B55: Two cleaning machines imported last year – NOT YET INSTALLED.
A56: Urgency | B56: Installation critical before sesame season (June).
A57: Warehouses | B57: Warehouses in Nacala are being rented.
A58: Installation Team | B58: Osama's team – Visa process to start immediately.
A59: Target | B59: Installation complete by Mid-May (ideally 15–20 May).
A60: Action | B60: Sidahmed to send visa details to Antu by email the same day.
A63: 11. IMMEDIATE ACTIONS & NEXT STEPS (YOUR CHECKLIST)
A64: Owner | B64: Action | C64: Deadline | D64: Status
A65: Elina + Manoj + Sidahmed | B65: Meet urgently to build working draft costing sheets for Soybeans and Mung Beans | C65: SAME DAY | D65: ☐ Done
A66: Elina | B66: Deliver working draft: Soybeans costing sheet (Nacala) | C66: End of Day | D66: ☐ Draft 1 Done
A67: Elina | B67: Deliver working draft: Mung Beans costing sheet (Nacala) | C67: End of Day | D67: ☐ Draft 1 Done
A68: Elina | B68: Prepare Beira versions of both sheets | C68: Day 2 | D68: ☐ After when info available
A69: Manoj | B69: Provide market purchase prices for Soybeans and Mung Beans | C69: Immediately | D69: ☐ Pending
A70: Sidahmed / Ops | B70: Validate completeness of cost components and confirm rates | C70: End of Day | D70: ☐ Pending
A71: Ops | B71: Clarify warehouse assignments by commodity + capacity/seasonal assumptions | C71: End of Day | D71: ☐ Pending
A72: Ops | B72: Finalise warehouse readiness for machine installation | C72: Ongoing | D72: ☐ Pending
A73: Elina | B73: Peanut costing sheet – follow same template once soybean/mung done | C73: After above | D73: ☐ Pending
A75: 12. OPEN ITEMS / TO BE MONITORED
A76: • Final confirmation of warehouse cost allocation rules in practice.
A77: • Possible availability of a Sortex machine (mentioned but not yet planned).
A78: • Peanut costing to follow same template once soybean/mung bean sheets are finalised.

Sheet Peanuts – Nacala
A1: MOZAMBIQUE – PEANUTS FORWARD-LOOKING COSTING SHEET | I1: ASSUMPTIONS & BASIS
A2: MAY 2026 Forward-looking Analysis | Nacala Commodity Business | I2: Parameter | J2: UOM | K2: Value | L2: To be updated by | M2: Notes/Comments
A3: COST BREAKDOWN | I3: Planned Qty | J3: MT | K3: 2000 | L3: Manoj Saini/Antu | M3: Full Purchasing Plan Provided by Mr. Antu
A4: Category | C4: Cost Item | D4: MZN/MT | E4: USD/MT | F4: Total MZN | G4: Notes / Source | I4: FX Rate | J4: MZN/USD | K4: 71 | L4: Elina Chiluvane | M4: Current Purchasing Rate F1
A5: MATERIAL COSTS | C5: Peanuts Purchase Cost | D5: =68*1000 -> 68000 | E5: =D5/$K$4 -> 957.74648 | F5: =D5*K3 -> 136000000 | G5: Current Price provided by Mr. Manoj - 19th May 2026 | I5: Finance Cost | J5: % | K5: =14.75%/12*2.5 -> 0.030729167 | L5: Invictus Team | M5: Annual Rate:14.75% with Cash cycle 2.5 months
C6: Landing Costs | D6: =+SUM(D7:D9) -> 0 | E6: =D6/$K$4 -> 0 | F6: =D6*$K$3 -> 0 | G6: Only if District Warehouses used (To follow up rates with OPS for PP and Sesame seasons) | I6: Moisture Loss | J6: % | K6: 0.02 | L6: Manoj Saini | M6: Discussed with Invictus and Mr. Manoj
C7: o/w Transportation Costs | D7: 0 | E7: =+D7/$K$4 -> 0 | F7: =D7*$K$3 -> 0 | G7: Non applicable | I7: Production Yield | J7: % | K7: =1-0.02 -> 0.98 | L7: Manoj Saini
C8: o/w Documentation Costs | D8: 0 | E8: =+D8/$K$4 -> 0 | F8: =D8*$K$3 -> 0 | G8: Non applicable | I8: Government-declared FOB price | J8: USD | K8: 1000 | L8: Manoj Saini | M8: Government Reference Prices for May
C9: o/w Handling Costs | D9: 0 | E9: =+D9/$K$4 -> 0 | F9: =D9*$K$3 -> 0 | G9: Non applicable | I9: Indicative CFR Price | J9: USD | K9: 1200 | L9: Invictus Team | M9: To be updated by Invictus
C10: Moisture Loss | D10: =+D5*$K$6 -> 1360 | E10: =D10/$K$4 -> 19.15493 | F10: =D10*$K$3 -> 2720000 | I10: Equivalent FX | J10: MZN/USD | K10: =+D93/K9 -> 71.824997 | M10: It will adjust with new CFR
A11: Total Material Cost - MZN/MT | D11: =SUM(D5:D10)/K7 -> 70775.51 | E11: =SUM(E5:E10)/K7 -> 996.83817 | F11: =SUM(F5:F10)/K7 -> 1.4155102e+08
A12: PROCESSING/ REPACKING COSTS
C13: Offloading | D13: 29 | E13: =D13/K4 -> 0.4084507 | F13: =D13*K3 -> 58000 | G13: Labour/Estivas Nacala - Beira Rates to be confirmed with OPS
C14: Stacking - Labour | D14: 29 | E14: =D14/K4 -> 0.4084507 | F14: =D14*K3 -> 58000 | G14: Labour/Estivas Nacala - Beira Rates to be confirmed with OPS
C15: Shifting to machine intake | D15: 0 | E15: =D15/K4 -> 0 | F15: =D15*K3 -> 0 | G15: Labour/Estivas Nacala - To be confirmed
C16: Subtotal MZN/MT | D16: =+SUM(D13:D15) -> 58 | E16: =+SUM(E13:E15) -> 0.81690141 | F16: =+SUM(F13:F15) -> 116000
C18: Production Depreciation MZN/MT | D18: 0 | E18: =D18/K4 -> 0 | F18: =D18*K3 -> 0 | G18: Cleaning Machine /Processes 2.5 MT per hour - Not required
C20: Electricity consumption per hour | D20: 0 | E20: 0 | F20: 0 | G20: 25 KW consumed per Hour - Not required
C21: Unit Cost per KW | D21: 0 | E21: 0 | F21: 0 | G21: 10 MZN/KW - Not required
C22: Machine Capacity per Hour | D22: 0 | E22: 0 | F22: 0 | G22: 2.5 MT per hour/20MT per Day if 8h assumed
C23: Electricity cost per MT/MZN | D23: =+IFERROR(D20*D21/D22,0) -> 0 | E23: =D23/K4 -> 0 | F23: =D23*K3 -> 0
C25: Machine Labour Rate per Day | D25: 0 | E25: 0 | F25: =336*0.45*K3 -> 302400 | G25: Daily rate per worker - to be validated by OPS - 336*9/20*2000
C26: Labour Needs (workers/day) | D26: 0 | E26: 0 | F26: 0 | G26: Workers per day
C27: Machine hours per Day | D27: 0 | E27: 0 | F27: 0 | G27: Assumed 8hours/ To be validaded by OPS
C28: MT Processed per Day | D28: =2.5*D27 -> 0 | E28: 0 | F28: 0 | G28: Capacity × hours of utilization
C29: Machine Labour Cost per MT | D29: =IFERROR(D25*D26/D28,0) -> 0 | E29: =+D29/K4 -> 0 | F29: =+D29*K3 -> 0
C32: Repacking - Labour | D32: 29 | E32: =+D32/K4 -> 0.4084507 | F32: =+D32*K3 -> 58000 | G32: Labour/Estivas Nacala - Beira Rates to be confirmed with OPS
C33: Jute Bags | D33: =135*20 -> 2700 | E33: =D33/$K$4 -> 38.028169 | F33: =+D33*$K$3 -> 5400000 | G33: 50kg Jute Bags - Updated Price (May 2026) is 135MZN per Bag
C34: Label - Material (Export req.) | D34: =5*20 -> 100 | E34: =D34/$K$4 -> 1.4084507 | F34: =+D34*$K$3 -> 200000 | G34: Stickers acceptable - 5MZN per label
C35: Subtotal 1 - MZN/MT | D35: =+SUM(D32:D34) -> 2829 | E35: =+SUM(E32:E34) -> 39.84507 | F35: =+SUM(F32:F34) -> 5658000
C37: Weighing | D37: 29 | E37: =+D37/$K$4 -> 0.4084507 | F37: =+D37*K3 -> 58000 | G37: Required -Agreed
C38: Sewing - Labour Rate | D38: 11.2 | E38: =+D38/$K$4 -> 0.15774648 | F38: =+D38*$K$3 -> 22400 | G38: Charged per Shift/280MZN per shift - 280/500*20bags
C39: Labour requirement | D39: 1 | E39: 1 | F39: 1 | G39: 500 bags estimated per person
C40: Yarn (MZN/Roll) | D40: =1*20 -> 20 | E40: =+D40/$K$4 -> 0.28169014 | F40: =+D40*$K$3 -> 40000 | G40: Price per roll is 500 MZN- Assumed 500bags/roll - 500/500*20bags per MT (Yarn and type price to be confirmed)
C41: Subtotal 2 - MZN/MT | D41: =(D38*D39+D40)+D37 -> 60.2 | E41: =(E38*E39+E40)+E37 -> 0.84788732 | F41: =(F38*F39+F40)+F37 -> 120400
C43: Stacking - Labour | D43: 29 | E43: =+D43/$K$4 -> 0.4084507 | F43: =+D43*$K$3 -> 58000 | G43: Stacking happens twice in this commodity- need to repack
C44: Loading | D44: 29 | E44: =+D44/$K$4 -> 0.4084507 | F44: =+D44*$K$3 -> 58000
C45: Stuffing | D45: 29 | E45: =+D45/$K$4 -> 0.4084507 | F45: =+D45*$K$3 -> 58000
C46: Subtotal 3 - MZN/MT | D46: =+SUM(D43:D45) -> 87 | E46: =+SUM(E43:E45) -> 1.2253521 | F46: =+SUM(F43:F45) -> 174000
A49: Total Repackaging/ Processing Cost MZN-MT | D49: =+D35+D41+D46 -> 2976.2 | E49: =+E35+E41+E46 -> 41.91831 | F49: =+F35+F41+F46 -> 5952400
A52: TOTAL EX FACTORY COST | D52: =+D11+D49 -> 73751.71 | E52: =+E11+E49 -> 1038.7565 | F52: =+F11+F49 -> 1.4750342e+08
A54: CUSTOMS & CLEARANCE | C54: Shore Handling | D54: =+'Manica quotation'!F13*$K$4 -> 657.68421 | E54: =D54/$K$4 -> 9.2631579 | F54: =D54*$K$3 -> 1315368.4 | G54: Nacala Port Charges (Cfm)
C55: Port Weighbridge | D55: =+'Manica quotation'!F14*$K$4 -> 115.84211 | E55: =D55/$K$4 -> 1.6315789 | F55: =D55*$K$3 -> 231684.21 | G55: Nacala Port Charges (Cfm)
C56: Delivery & Reception of Empty Container | D56: =+'Manica quotation'!F15*$K$4 -> 56.052632 | E56: =D56/$K$4 -> 0.78947368 | F56: =D56*$K$3 -> 112105.26 | G56: Nacala Port Charges (Cfm)
C57: Agency Fee | D57: =+'Manica quotation'!F23*$K$4 -> 373.68421 | E57: =D57/$K$4 -> 5.2631579 | F57: =D57*$K$3 -> 747368.42 | G57: Handling Charges (Manica)
C58: Scanning / Kudumba | D58: =+'Manica quotation'!F26*$K$4 -> 224.21053 | E58: =D58/$K$4 -> 3.1578947 | F58: =D58*$K$3 -> 448421.05
C59: Miscellaneous / Facilitation Fees | D59: =+'Manica quotation'!F27*$K$4 -> 347.52632 | E59: =D59/$K$4 -> 4.8947368 | F59: =D59*$K$3 -> 695052.63 | G59: Customs Clearance & Others
C60: Tallying (incl. certificate) | D60: =+'Manica quotation'!F28*$K$4 -> 112.10526 | E60: =D60/$K$4 -> 1.5789474 | F60: =D60*$K$3 -> 224210.53 | G60: Customs Clearance & Others
C61: Fumigation — estimate per certificate | D61: =+'Manica quotation'!F29*$K$4 -> 130.78947 | E61: =D61/$K$4 -> 1.8421053 | F61: =D61*$K$3 -> 261578.95 | G61: Customs Clearance & Others
C62: Fetch Empty at Liner Depot → Shipper W/H → Port (Nacala city) | D62: =+'Manica quotation'!F32*$K$4 -> 896.84211 | E62: =D62/$K$4 -> 12.631579 | F62: =D62*$K$3 -> 1793684.2 | G62: Transport Charges
C63: Subtotal Customs and Forwarding - Export Cargo | D63: =+SUM(D54:D62) -> 2914.7368 | E63: =+SUM(E54:E62) -> 41.052632 | F63: =+SUM(F54:F62) -> 5829473.7 | G63: 079/MFSN/CNF/EXPORT/PA/2025 - Used as the best estimate - To be updated
C65: EXCLUDED CHARGES — Billed Per BL ( 10 containers each BL)
C66: Export Documentation | D66: =+'Manica quotation'!F35*$K$4 -> 65.394737 | E66: =D66/$K$4 -> 0.92105263 | F66: =D66*$K$3 -> 130789.47 | G66: Per BL ÷ C7 containers
C67: Customs Services Fee | D67: =+'Manica quotation'!F36*$K$4 -> 4.4842105 | E67: =D67/$K$4 -> 0.063157895 | F67: =D67*$K$3 -> 8968.4211 | G67: Per BL ÷ C7 containers
C68: Customs Brokerage | D68: =+'Manica quotation'!F37*$K$4 -> 74.736842 | E68: =D68/$K$4 -> 1.0526316 | F68: =D68*$K$3 -> 149473.68 | G68: Per BL ÷ C7 containers
C69: MCNet / Declaration (FOB >$50,000) | D69: =+'Manica quotation'!F38*$K$4 -> 23.915789 | E69: =D69/$K$4 -> 0.33684211 | F69: =D69*$K$3 -> 47831.579 | G69: Per BL ÷ C7 containers
C70: Phytosanitary Certificate | D70: =+'Manica quotation'!F39*$K$4 -> 29.894737 | E70: =D70/$K$4 -> 0.42105263 | F70: =D70*$K$3 -> 59789.474 | G70: Per BL ÷ C7 containers
C71: Phytosanitary Inspector Dislocation | D71: =+'Manica quotation'!F40*$K$4 -> 18.684211 | E71: =D71/$K$4 -> 0.26315789 | F71: =D71*$K$3 -> 37368.421 | G71: Per BL ÷ C7 containers
C72: Certificate of Origin & LDC | D72: =+'Manica quotation'!F41*$K$4 -> 29.894737 | E72: =D72/$K$4 -> 0.42105263 | F72: =D72*$K$3 -> 59789.474 | G72: Per BL ÷ C7 containers
C73: Sample Collection & Analysis (per lot) | D73: =945/250*$K$4 -> 268.38 | E73: =+D73/$K$4 -> 3.78 | F73: =D73*$K$3 -> 536760 | G73: ($945/lot)
C74: Craft Paper & Dry Bags ($75/container) | D74: =75/25*K4 -> 213 | E74: =+D74/$K$4 -> 3 | F74: =D74*$K$3 -> 426000 | G74: ($75 PER container)
C75: Subtotal Customs and Forwarding - Export Cargo | D75: =+SUM(D66:D74) -> 728.38526 | E75: =+SUM(E66:E74) -> 10.258947 | F75: =+SUM(F66:F72) -> 494010.53 | G75: 079/MFSN/CNF/EXPORT/PA/2025 - Used as the best estimate - To be updated
A77: Total Customs Cost- MZN/MT | D77: =+D75+D63 -> 3643.1221 | E77: =+E75+E63 -> 51.311579 | F77: =+F75+F63 -> 6323484.2 | G77: 079/MFSN/CNF/EXPORT/PA/2025
A79: FINANCE | C79: Finance Cost (14.75% p.a., 2.5-month cycle) | D79: =(D52)*K5 -> 2266.3286 | E79: =D79/K4 -> 31.920121 | F79: =D79*K3 -> 4532657.2 | G79: Applied on material cost
A80: CONTINGENCY | C80: Other Contingencies (5%) | D80: =((D49+D103)*5%) -> 176.02686 | E80: =D80/$K$4 -> 2.4792515 | F80: =D80*K3 -> 352053.72 | G80: 5% of processing + customs + Opex of the total costs
A81: TOTAL FOB COST / MT | D81: =+D52+D77+SUM(D79:D80) -> 79837.188 | E81: =D81/$K$4 -> 1124.4674 | F81: =D81*$K$3 -> 1.5967438e+08
A83: CIF CHARGES | C83: Terminal Handling (THC) | D83: =+'Manica quotation'!F18*$K$4*0 -> 0 | E83: =D83/$K$4*0 -> 0 | F83: =D83*$K$3 -> 0 | G83: Shipping Line Charges (Msc) - Included in $48 USD Freight cost
C84: Seal | D84: =+'Manica quotation'!F19*$K$4*0 -> 0 | E84: =D84/$K$4*0 -> 0 | F84: =D84*$K$3 -> 0 | G84: Shipping Line Charges (Msc) - Included in $48 USD Freight cost
C85: Container Release (Lift On Fee) | D85: =+'Manica quotation'!F20*$K$4*0 -> 0 | E85: =D85/$K$4*0 -> 0 | F85: =D85*$K$3 -> 0 | G85: Shipping Line Charges (Msc) - Included in $48 USD Freight cost
C86: Shipping Charges | D86: =+SUM(D83:D85) -> 0 | E86: =+SUM(E83:E85) -> 0 | F86: =+SUM(F83:F85) -> 0 | G86: 079/MFSN/CNF/EXPORT/PA/2025
A88: FREIGHT COST | C88: ICM Charge (2.5%/MT) | D88: =+E88*K4 -> 1775 | E88: =2.5/100*K8 -> 25 | F88: =D88*K3 -> 3550000 | G88: On FOB price/Governmen
C89: Stock Insurance (0.15% of FOB) | D89: =+D81*0.0015 -> 119.75578 | E89: =D89/$K$4 -> 1.6867011 | F89: =+D89*K3 -> 239511.56 | G89: Applied on USD FOB/MT
C90: Freight Cost | D90: =+E90*K4 -> 4458.0526 | E90: 62.789474 | F90: =+D90*K4 -> 316521.74 | G90: Jakarta 1193$/20ft this was in Apr (Can be updated)
A91: FREIGHT COST - MZN/MT | C91: Ocean Freight Cost | D91: =+SUM(D88:D90) -> 6352.8084 | E91: =+D91/K4 -> 89.476175 | F91: =+D91*K3 -> 12705617
A93: GROSS PROFIT MARGIN | C93: Total COGS/CFR Cost per MT | D93: =+D81+D91 -> 86189.996 | E93: =+D93/$K$4 -> 1213.9436 | F93: =+D93*$K$3 -> 1.7237999e+08 | G93: MT
C94: Total COGS/CFR Cost per bag | D94: =+D93/$D$118 -> 4309.4998 | E94: =+D94/$K$4 -> 60.69718 | F94: =+D94*$K$3 -> 8618999.6 | G94: Unit
C95: Gross Profit per MT | D95: =+($K$9*$K$4)-D93 -> -989.99618 | E95: =+D95/$K$4 -> -13.943608 | F95: =+D95*$K$3 -> -1979992.4 | G95: Unit
C96: Gross Margin | D96: =+D95/(K9*K4) -> -0.011619673 | E96: =+E95/K9 -> -0.011619673 | F96: =+F95/(K9*K4*K3) -> -0.011619673 | G96: %
A99: OPEX | C99: Warehouse Costs | D99: =('1. OPEX Inputs'!H13*C122+'1. OPEX Inputs'!H13*D122+'1. OPEX Inputs'!H13*E122)/K3 -> 337.36571 | E99: =D99/$K$4 -> 4.7516298 | F99: =D99*$K$3 -> 674731.43 | G99: Allocation rate*cost/MT/Based on new warehouse rates/2.5 months - In general this needs a revision
C100: Employment Costs | D100: =176912.625697584/K3 -> 88.456313 | E100: =D100/$K$4 -> 1.2458636 | F100: =D100*$K$3 -> 176912.63 | G100: Allocation rate*cost/MT
C101: Other General and Admin Costs | D101: {=(SUM('1. OPEX Inputs'!H16:H20)*C122+SUM('1. OPEX Inputs'!H16:H20)*D122+SUM('1. OPEX Inputs'!H16:H20*E122))/$K$3} -> 96.327667 | E101: =D101/$K$4 -> 1.3567277 | F101: =D101*$K$3 -> 192655.33 | G101: Allocation rate*cost/MT
C102: Depreciation | D102: =+(C121*C122+C121*D122+C121*E122)/K3 -> 22.1875 | E102: =D102/$K$4 -> 0.3125 | F102: =D102*$K$3 -> 44375 | G102: Vehicle Depreciation*Allocation rate/MT
A103: Total OPEX MZN/MT | D103: =SUM(D99:D102) -> 544.33719 | E103: =SUM(E99:E102) -> 7.666721 | F103: =SUM(F99:F102) -> 1088674.4
A107: NET PROFIT MARGIN | C107: Total Cost per MT | D107: =+D93+D103 -> 86734.333 | E107: =+D107/$K$4 -> 1221.6103 | F107: =+D107*$K$3 -> 1.7346867e+08 | G107: MT
C108: Total Cost per bag | D108: =+D107/$D$118 -> 4336.7167 | E108: =+D108/$K$4 -> 61.080516 | F108: =+D108*$K$3 -> 8673433.3 | G108: Unit
C109: Net Profit per MT | D109: =+($K$9*$K$4)-D107 -> -1534.3334 | E109: =+D109/$K$4 -> -21.610329 | F109: =+D109*$K$3 -> -3068666.7 | G109: Unit
C110: Gross Margin | D110: =+D109/SUM($K$4*$K$9) -> -0.018008608 | E110: =+E109/K9 -> -0.018008608 | F110: =+F109/(K9*K4*K3) -> -0.018008608 | G110: %
A113: TOTAL CIF COST / MT (USD) | E113: =+E107 -> 1221.6103
C115: Weight Per Unit | D115: 50 | G115: 50kg per BAG
C116: Number of Units (bags) | D116: =+D117/D115 -> 40000 | G116: All shipments
C117: Total Weight | D117: =+K3*1000 -> 2000000 | G117: In KG
C118: Units/MT | D118: =1000/D115 -> 20 | G118: Nr. Of Bags per MT
A120: Notes
A121: SGA Depreciation (Per Month) | C121: 44375
A122: Allocation rates (full cycle) | C122: 0.4 | D122: 0.4 | E122: =40%/2 -> 0.2
A124: COLOUR LEGEND
A125: Column C= Input data (update per purchase)
A126: Column D+E = Formula / calculated Columns
A127: Italic = Notes / source / confirmation needed

Sheet Sesame – Nacala
A1: MOZAMBIQUE – SESAME FORWARD-LOOKING COSTING SHEET | H1: ASSUMPTIONS & BASIS
A2: MAY 2026 Forward-looking Analysis | Nacala Commodity Business | H2: Parameter | I2: UOM | J2: Value | K2: To be updated by | L2: Notes/Comments
A3: COST BREAKDOWN | H3: Planned Qty | I3: MT | J3: 11000 | K3: Manoj Saini/Antu | L3: Purchasing Plan Provided by Mr. Antu
A4: Category | B4: Cost Item | C4: MZN/MT | D4: USD/MT | E4: Total MZN | F4: Notes / Source | H4: FX Rate | I4: MZN/USD | J4: 71 | K4: Elina Chiluvane | L4: Current Purchasing Rate F1
A5: MATERIAL COSTS | B5: Sesame seeds Purchase Cost | C5: 80000 | D5: =C5/$J$4 -> 1126.7606 | E5: =C5*J3 -> 880000000 | F5: Current Price provided by Mr. Manoj (19th May2026) | H5: Finance Cost | I5: % | J5: =14.75%/12*2.5 -> 0.030729167 | K5: Elina Chiluvane | L5: Annual Rate:14.75% with Cash cycle 2.5 months
B6: Landing Costs | C6: =+SUM(C7:C9) -> 0 | D6: =C6/J4 -> 0 | E6: =C6*$J$3 -> 0 | F6: We will not use district warehouses in this Sesame season | H6: Moisture Loss | I6: % | J6: 0.01 | K6: Invictus team
B7: o/w Transportation Costs | C7: 0 | D7: =+C7/$J$4 -> 0 | E7: =C7*$J$3 -> 0 | F7: Non applicable | H7: Production Yield | I7: % | J7: =1-0.04 -> 0.96 | K7: Manoj Saini/Invictus | L7: 4% Production Loss
B8: o/w Documentation Costs | C8: 0 | D8: =+C8/$J$4 -> 0 | E8: =C8*$J$3 -> 0 | F8: Non applicable | H8: Government-declared FOB price | I8: USD | J8: 1400 | K8: Manoj Saini | L8: Government Reference Prices for May
B9: o/w Handling Costs | C9: 0 | D9: =+C9/$J$4 -> 0 | E9: =C9*$J$3 -> 0 | F9: Non applicable | H9: Indicative CFR Price | I9: USD | J9: 1400 | K9: Invictus team | L9: Provided by Invictus
B10: Moisture Loss | C10: =+C5*$J$6 -> 800 | D10: =C10/J4 -> 11.267606 | E10: =C10*J3 -> 8800000 | F10: Tipically due to storage - Usualy Not more than 1% and if turnover is high=0 | H10: Equivalent FX | I10: MZN/USD | J10: =+C88/J9 -> 70.620257 | L10: It will adjust with new CFR
A11: Total Material Cost - MZN/MT | C11: =SUM(C5:C10)/J7 -> 84166.667 | D11: =+C11/J4 -> 1185.446 | E11: =+C11*J3 -> 9.2583333e+08
A13: PROCESSING COSTS | B13: Offloading | C13: 29 | D13: =C13/$J$4 -> 0.4084507 | E13: =C13*$J$3 -> 319000 | F13: Labour/Estivas Nacala - Beira Rates to be confirmed with OPS
B14: Stacking - Labour | C14: 29 | D14: =C14/$J$4 -> 0.4084507 | E14: =C14*$J$3 -> 319000 | F14: Labour/Estivas Nacala - Beira Rates to be confirmed with OPS
B15: Shifting to machine intake (2x) | C15: =29*2 -> 58 | D15: =C15/$J$4 -> 0.81690141 | E15: =C15*$J$3 -> 638000 | F15: This process involves two movements, of 29MZN each
B16: Subtotal MZN/MT | C16: =+SUM(C13:C15) -> 116 | D16: =+SUM(D13:D15) -> 1.6338028 | E16: =+SUM(E13:E15) -> 1276000
B18: Production Depreciation MZN/MT | C18: =+(C115*C117+C115*D117+C115*E117+C115*F117)/$J$3 -> 4.6980902 | D18: =C18/J4 -> 0.066170285 | E18: =C18*J3 -> 51678.993 | F18: Sesame is cleaned
B20: Electricity consumption per hour | C20: 25 | D20: 0 | E20: 0 | F20: 25 KW consumed per Hour
B21: Unit Cost per KW | C21: 10 | D21: 0 | E21: 0 | F21: 10 MZN/KW
B22: Machine Capacity per Hour | C22: 2.5 | D22: 0 | E22: 0 | F22: 2.5 MT per hour/20MT per Day
B23: Electricity cost per MT/MZN | C23: =+IFERROR(C20*C21/C22,0) -> 100 | D23: =C23/J4 -> 1.4084507 | E23: =C23*J3 -> 1100000
B25: Machine Labour Rate per Day | C25: 336 | D25: =+C25/J4 -> 4.7323944 | E25: 0 | F25: Daily rate per worker
B26: Labour Needs (workers/day) | C26: 9 | D26: 9 | E26: 0 | F26: Workers per day
B27: Machine hours per Day | C27: 8 | D27: 8 | E27: 0 | F27: Assumed 8hours per day
B28: MT Processed per Day | C28: =2.5*C27 -> 20 | D28: 20 | E28: 0 | F28: Capacity × hours of utilization
B29: Machine Labour Cost per MT | C29: =+(C25*C26)/C28 -> 151.2 | D29: =+(D25*D26)/D28 -> 2.1295775 | E29: =+C29*J3 -> 1663200
A31: Total Processing Cost - MZN/MT | C31: =+C16+C18+C23+C29 -> 371.89809 | D31: =+D16+D18+D23+D29 -> 5.2380013 | E31: =+E16+E18+E23+E29 -> 4090879
A33: PACKAGING COSTS | B33: Sewing - Labour Rate | C33: =0.56*20 -> 11.2 | D33: =+C33/J4 -> 0.15774648 | E33: =+C33*$J$3 -> 123200 | F33: Charged per Shift/280MZN per shift - 280/500*20bags
B34: Labour requirement | C34: 1 | D34: 1 | E34: 1 | F34: 500 bags estimated per person
B35: Yarn (MZN/Roll) | C35: =1*20 -> 20 | D35: =+C35/J4 -> 0.28169014 | E35: =+C35*$J$3 -> 220000 | F35: Price per roll is 500 MZN- Assumed 500bags/roll - 500/500*20bags per MT (Yarn price to be confirmed)
B36: Subtotal MZN/MT | C36: =+C33*C34+C35 -> 31.2 | D36: =+D33*D34+D35 -> 0.43943662 | E36: =+E33*E34+E35 -> 343200
B38: After Processing Stacking - Labour | C38: 0 | D38: =+C38/J4 -> 0 | E38: =+C38*J3 -> 0 | F38: Non applicable
B40: Packing - Labour | C40: 0 | D40: =+C40/J4 -> 0 | E40: =+C40*J3 -> 0 | F40: Non applicable/Machine sewing
B41: Packaging Bags | C41: =22*20 -> 440 | D41: =C41/$J$4 -> 6.1971831 | E41: =+C41*$J$3 -> 4840000 | F41: Current Purchasing price (22MZN per bag - Same as PP)
B42: Label - Material (Export req.) | C42: =500/19 -> 26.315789 | D42: =C42/$J$4 -> 0.37064492 | E42: =+C42*$J$3 -> 289473.68 | F42: Stickers not acceptable for China- Will use paper Label - 500mzn per container of 19MT
A44: Total Packaging Cost MZN-MT | C44: =+SUM(C40:C42)+C36+C38 -> 497.51579 | D44: =+SUM(D40:D42)+D36+D38 -> 7.0072646 | E44: =+SUM(E40:E42)+E36+E38 -> 5472673.7
A46: AFTER PACK COSTS | B46: Shifting from Production to stacking area - Labour | C46: 58 | D46: =+C46/$J$4 -> 0.81690141 | E46: =+C46*$J$3 -> 638000 | F46: This process involves two movements, of 29MZN each
B47: Loading | C47: 29 | D47: =+C47/$J$4 -> 0.4084507 | E47: =+C47*$J$3 -> 319000
B48: Stuffing | C48: 29 | D48: =+C48/$J$4 -> 0.4084507 | E48: =+C48*$J$3 -> 319000
C49: =+SUM(C46:C48) -> 116 | D49: =+SUM(D46:D48) -> 1.6338028 | E49: =+SUM(E46:E48) -> 1276000
A51: TOTAL EX FACTORY COST | C51: =+C11+C31+C44+C49 -> 85152.081 | D51: =+D11+D31+D44+D49 -> 1199.3251 | E51: =+E11+E31+E44+E49 -> 9.3667289e+08
A53: CUSTOMS & CLEARANCE | B53: Shore Handling | C53: =+'Manica quotation'!F13*$J$4 -> 657.68421 | D53: =C53/$J$4 -> 9.2631579 | E53: =C53*$J$3 -> 7234526.3 | F53: Nacala Port Charges (Cfm)/To be updated
B54: Port Weighbridge | C54: =+'Manica quotation'!F14*$J$4 -> 115.84211 | D54: =C54/J4 -> 1.6315789 | E54: =C54*J3 -> 1274263.2 | F54: Nacala Port Charges (Cfm) / To be updated
B55: Delivery & Reception of Empty Container | C55: =+'Manica quotation'!F15*$J$4 -> 56.052632 | D55: =C55/J4 -> 0.78947368 | E55: =C55*J3 -> 616578.95 | F55: Nacala Port Charges (Cfm)/ To be updated
B56: Agency Fee | C56: =+'Manica quotation'!F23*$J$4 -> 373.68421 | D56: =C56/J4 -> 5.2631579 | E56: =C56*J3 -> 4110526.3 | F56: Handling Charges (Manica) / To be updated
B57: Scanning / Kudumba | C57: =+'Manica quotation'!F26*$J$4 -> 224.21053 | D57: =C57/J4 -> 3.1578947 | E57: =C57*J3 -> 2466315.8 | F57: Customs Clearance & Others / To be updated
B58: Miscellaneous / Facilitation Fees | C58: =+'Manica quotation'!F27*$J$4 -> 347.52632 | D58: =C58/J4 -> 4.8947368 | E58: =C58*J3 -> 3822789.5 | F58: Customs Clearance & Others / To be updated
B59: Tallying (incl. certificate) | C59: =+'Manica quotation'!F28*$J$4 -> 112.10526 | D59: =C59/J4 -> 1.5789474 | E59: =C59*J3 -> 1233157.9 | F59: Customs Clearance & Others / To be updated
B60: Fumigation — estimate per certificate | C60: =+'Manica quotation'!F29*$J$4 -> 130.78947 | D60: =C60/J4 -> 1.8421053 | E60: =C60*J3 -> 1438684.2 | F60: Customs Clearance & Others / To be updated
B61: Fetch Empty at Liner Depot → Shipper W/H → Port (Nacala city) | C61: =+'Manica quotation'!F32*J4 -> 896.84211 | D61: =C61/$J$4 -> 12.631579 | E61: =C61*J3 -> 9865263.2 | F61: Transport Charges / To be updated
B62: Subtotal Customs and Forwarding - Export Cargo | C62: =+SUM(C53:C61) -> 2914.7368 | D62: =+SUM(D53:D61) -> 41.052632 | E62: =+SUM(E53:E61) -> 32062105 | F62: 079/MFSN/CNF/EXPORT/PA/2025 - Used as the best estimate - To be updated
B64: EXCLUDED CHARGES — Billed Per BL (10 Containers per BL)
B65: Export Documentation | C65: =+'Manica quotation'!F35*$J$4 -> 65.394737 | D65: =C65/$J$4 -> 0.92105263 | E65: =C65*$J$3 -> 719342.11 | F65: Per BL ÷ C7 containers
B66: Customs Services Fee | C66: =+'Manica quotation'!F36*$J$4 -> 4.4842105 | D66: =C66/$J$4 -> 0.063157895 | E66: =C66*$J$3 -> 49326.316 | F66: Per BL ÷ C7 containers
B67: Customs Brokerage | C67: =+'Manica quotation'!F37*$J$4 -> 74.736842 | D67: =C67/$J$4 -> 1.0526316 | E67: =C67*$J$3 -> 822105.26 | F67: Per BL ÷ C7 containers
B68: MCNet / Declaration (FOB >$50,000) | C68: =+'Manica quotation'!F38*$J$4 -> 23.915789 | D68: =C68/$J$4 -> 0.33684211 | E68: =C68*$J$3 -> 263073.68 | F68: Per BL ÷ C7 containers
B69: Phytosanitary Certificate | C69: =+'Manica quotation'!F39*$J$4 -> 29.894737 | D69: =C69/$J$4 -> 0.42105263 | E69: =C69*$J$3 -> 328842.11 | F69: Per BL ÷ C7 containers
B70: Phytosanitary Inspector Dislocation | C70: =+'Manica quotation'!F40*$J$4 -> 18.684211 | D70: =C70/$J$4 -> 0.26315789 | E70: =C70*$J$3 -> 205526.32 | F70: Per BL ÷ C7 containers
B71: Certificate of Origin & LDC | C71: =+'Manica quotation'!F41*$J$4 -> 29.894737 | D71: =C71/$J$4 -> 0.42105263 | E71: =C71*$J$3 -> 328842.11 | F71: Per BL ÷ C7 containers
B72: Sample Collection & Analysis (per lot) | C72: =+'Peanuts – Nacala'!D73 -> 268.38 | D72: =C72/$J$4 -> 3.78 | E72: =C72*$J$3 -> 2952180 | F72: ($945/lot)
B73: Craft Paper & Dry Bags ($75/container) | C73: =+'Peanuts – Nacala'!D74 -> 213 | D73: =C73/$J$4 -> 3 | E73: =C73*$J$3 -> 2343000 | F73: ($75 PER container)
B74: Subtotal Customs and Forwarding - Export Cargo | C74: =+SUM(C65:C73) -> 728.38526 | D74: =+SUM(D65:D73) -> 10.258947 | E74: =+SUM(E65:E73) -> 8012237.9
A76: Total Customs Cost- MZN/MT | C76: =+C74+C62 -> 3643.1221 | D76: =+D74+D62 -> 51.311579 | E76: =+E74+E62 -> 40074343 | F76: 079/MFSN/CNF/EXPORT/PA/2025 - Used as the best estimate - To be updated
A78: FINANCE | B78: Finance Cost (14.75% p.a., 2.5-month cycle) | C78: =(C51)*J5 -> 2616.6525 | D78: =C78/J4 -> 36.85426 | E78: =C78*J3 -> 28783177 | F78: Applied on material cost
A79: CONTINGENCY | B79: Other Contingencies (5%) | C79: =((C31+C44+C97)*5%) -> 54.883614 | D79: =C79/J4 -> 0.77300865 | E79: =C79*J3 -> 603719.75 | F79: 5% of processing + customs + Opex of the total costs
A81: TOTAL FOB COST / MT | C81: =+C51+C76+SUM(C78:C79) -> 91466.739 | D81: =+D51+D76+SUM(D78:D79) -> 1288.2639 | E81: =+E51+E76+E97+SUM(E78:E79) -> 1.008645e+09
A83: FREIGHT COST | B83: Export Levy (2.5%) | C83: =+D83*J4 -> 2485 | D83: =2.5/100*J8 -> 35 | E83: =C83*J3 -> 27335000 | F83: On Government declared price
B84: Stock Insurance (0.15% of FOB) | C84: =0.0015*C81 -> 137.20011 | D84: =D81*0.15% -> 1.9323959 | E84: =D84*J3*J4 -> 1509201.2 | F84: Applied on USD FOB/MT
B85: Freight Cost | C85: =+D85*J4 -> 4779.4211 | D85: 67.315789 | E85: =D85*J4*J5 -> 146.86763 | F85: $1279/container provided by Invictus (latest available and may be updated) - To China
A86: FREIGHT COST - MZN/MT | B86: Ocean Freight Cost | C86: =+SUM(C83:C85) -> 7401.6212 | D86: =+C86/J4 -> 104.24819 | E86: =+C86*J3 -> 81417833
A88: GROSS PROFIT MARGIN | B88: Total COGS/CFR Cost per MT | C88: =+C81+C86 -> 98868.36 | D88: =+C88/$J$4 -> 1392.5121 | E88: =+C88*$J$3 -> 1.087552e+09 | F88: MT
B89: Total COGS/CFR Cost per bag | C89: =+C88/$C$109 -> 4943.418 | D89: =+C89/$J$4 -> 69.625606 | E89: =+C89*$J$3 -> 54377598 | F89: Unit
B90: Gross Profit per MT | C90: =+($J$9*$J$4)-C88 -> 531.6401 | D90: =+C90/$J$4 -> 7.4878887 | E90: =+C90*$J$3 -> 5848041.1 | F90: Unit
B91: Gross Margin | C91: =+C90/(J9*J4) -> 0.0053484919 | D91: =+D90/$J$9 -> 0.0053484919 | E91: =+E90/(J9*J4*J3) -> 0.0053484919 | F91: %
A93: OPEX | B93: Warehouse Costs | C93: =+('1. OPEX Inputs'!H13*C117+'1. OPEX Inputs'!H13*D117+'1. OPEX Inputs'!H13*E117+F117*'1. OPEX Inputs'!H13)/J3 -> 155.81594 | D93: =C93/J4 -> 2.1945907 | E93: =C93*J3 -> 1713975.4 | F93: Allocation rate*cost/MT/Based on new warehouse rates
B94: Employment Costs | C94: =+SUM('1. OPEX Inputs'!H15*C117+'1. OPEX Inputs'!H15*D117+'1. OPEX Inputs'!H15*E117+'1. OPEX Inputs'!H15*F117)/J3 -> 17.704965 | D94: =C94/J4 -> 0.24936571 | E94: =C94*J3 -> 194754.62 | F94: Allocation rate*cost/MT
B95: Other General and Admin Costs | C95: =((SUM('1. OPEX Inputs'!H16:H20)*C117+SUM('1. OPEX Inputs'!H16:H20)*D117+SUM('1. OPEX Inputs'!H16:H20)*E117+SUM('1. OPEX Inputs'!H16:H20)*F117))/J3 -> 44.489957 | D95: =C95/J4 -> 0.62661911 | E95: =C95*J3 -> 489389.53 | F95: Allocation rate*cost/MT
B96: Depreciation | C96: =+(C116*C117+C116*D117+C116*E117+C116*F117)/J3 -> 10.247533 | D96: =C96/J4 -> 0.14433145 | E96: =C96*J3 -> 112722.86 | F96: Vehicle Depreciation*Allocation rate/MT
A97: Total OPEX MZN/MT | C97: =SUM(C93:C96) -> 228.2584 | D97: =SUM(D93:D96) -> 3.214907 | E97: =SUM(E93:E96) -> 2510842.4
A100: NET PROFIT MARGIN | B100: Total Cost per MT | C100: =+C88+C97 -> 99096.618 | D100: =+C100/$J$4 -> 1395.727 | E100: =+C100*$J$3 -> 1.0900628e+09 | F100: MT
B101: Total Cost per bag | C101: =+C100/C109 -> 4954.8309 | D101: =+C101/$J$4 -> 69.786351 | E101: =+C101*$J$3 -> 54503140 | F101: Unit
B102: Net Profit per MT | C102: =+($J$9*$J$4)-C100 -> 303.3817 | D102: =+C102/$J$4 -> 4.2729817 | E102: =+C102*$J$3 -> 3337198.7 | F102: Unit
B103: Gross Margin | C103: =+C102/SUM($J$4*$J$9) -> 0.0030521298 | D103: =+D102/J9 -> 0.0030521298 | E103: =+E102/(J9*J4*J3) -> 0.0030521298 | F103: %
B106: Weight Per Unit | C106: 50 | F106: 50kg per BAG
B107: Number of Units (bags) | C107: =+C108/C106 -> 220000 | F107: All shipments
B108: Total Weight in KG | C108: =+J3*1000 -> 11000000 | F108: In KG
B109: Units/MT | C109: =1000/C106 -> 20 | F109: Nr. Of Bags per MT
A113: TOTAL CIF COST / MT (USD) | D113: =+D100 -> 1395.727
A115: COGS Depreciation (Per Month) | C115: 20344.19
A116: SGA Depreciation (Per Month) | C116: 44375
A117: Allocation Rate per Month | C117: 0.37199437 | D117: 0.7844006 | E117: 0.94480736 | F117: 0.43903115
A118: Months | C118: May | D118: June | E118: July | F118: August
A120: COLOUR LEGEND
A121: Column C= Input data (update per purchase)
A122: Column D+E = Formula / calculated Columns
A123: Italic = Notes / source / confirmation needed

Sheet Soy Beans – Nacala
A1: MOZAMBIQUE – SOY BEANS FORWARD-LOOKING COSTING SHEET | H1: ASSUMPTIONS & BASIS
A2: APRIL/MAY 2026 Forward-looking Analysis | Beira Commodity Business | H2: Parameter | I2: UOM | J2: Value | K2: To be updated by | L2: Notes/Comments
A3: COST BREAKDOWN | H3: Planned Qty | I3: MT | J3: 2000 | K3: Manoj Saini/Antu | L3: Purchasing Plan Provided by Mr. Antu
A4: Category | B4: Cost Item | C4: MZN/MT | D4: USD/MT | E4: Total MZN | F4: Notes / Source | H4: FX Rate | I4: MZN/USD | J4: 71 | K4: Elina Chiluvane
A5: MATERIAL COSTS | B5: Soy Beans Purchase Cost | C5: 36400 | D5: =C5/J4 -> 512.67606 | E5: =C5*J3 -> 72800000 | F5: Updated change from 35,000 to 36,400 based average purchase price | H5: Finance Cost | I5: % | J5: =14.75%/12*2.5 -> 0.030729167 | K5: Elina Chiluvane | L5: Annual Rate:14.75% with Cash cycle 2.5months
B6: Landing Costs | C6: =+SUM(C7:C9) -> 0 | D6: =C6/J4 -> 0 | E6: =C6*$J$3 -> 0 | F6: Only if District Warehouses used (To follow up rates with OPS for PP and Sesame seasons) | H6: Moisture Loss | I6: % | J6: 0.01 | K6: Manoj Saini | L6: Not more than 1% - if high turnover 0 - Small for mosture or repacking only
B7: o/w Transportation Costs | C7: 0 | D7: =+C7/$J$4 -> 0 | E7: =C7*$J$3 -> 0 | F7: Non applicable | H7: Production Yield | I7: % | J7: =1-0.01 -> 0.99 | K7: Manoj Saini | L7: 1% no cleaning needed- Small for moisture or repacking only
B8: o/w Documentation Costs | C8: 0 | D8: =+C8/$J$4 -> 0 | E8: =C8*$J$3 -> 0 | F8: Non applicable | H8: Government-declared FOB price | I8: USD | J8: 550
B9: o/w Handling Costs | C9: 0 | D9: =+C9/$J$4 -> 0 | E9: =C9*$J$3 -> 0 | F9: Non applicable | H9: Indicate CFR Price | I9: USD | J9: =J17 -> 693.13725
B10: Moisture Loss | C10: =+C5*$J$6 -> 364 | D10: =C10/J4 -> 5.1267606 | E10: =C10*J3 -> 728000 | F10: Tipically due to storage - Usualy Not more than 1% and if turnover is high=0 | H10: Equivalent FX | I10: MZN/USD | J10: =+C91/J9 -> 68.403525
A11: Total Material Cost - MZN/MT | C11: =SUM(C5:C10)/J7 -> 37135.354 | D11: =SUM(D5:D10) -> 517.80282 | E11: =SUM(E5:E10) -> 73528000
J12: =460+230+230+230 -> 1150
A13: PROCESSING COSTS | B13: Offloading | C13: 29 | D13: =C13/J4 -> 0.4084507 | E13: =C13*J3 -> 58000 | F13: Labour/Estivas Nacala - Beira Rates to be confirmed with OPS
B14: Stacking - Labour | C14: 29 | D14: =C14/J4 -> 0.4084507 | E14: =C14*J3 -> 58000 | F14: Labour/Estivas Nacala - Beira Rates to be confirmed with OPS
B15: Repacking | C15: 29 | D15: =C15/J4 -> 0.4084507 | E15: =C15*$J$3 -> 58000 | F15: Labour/To be confirmed by Mohamed | H15: Price from Invictus to Customer | J15: =J16*102/100 -> 721.14 | L15: 1% sales commission & other cost
B16: Weighing | C16: 29 | D16: =C16/J4 -> 0.4084507 | E16: =C16*$J$3 -> 58000 | H16: Price from Aquila to Invictus | J16: 707 | K16: Provided by Invictus
B17: Subtotal MZN/MT | C17: =+SUM(C13:C16) -> 116 | D17: =+SUM(D13:D16) -> 1.6338028 | E17: =+SUM(E13:E16) -> 232000 | H17: Price from Merec to Aquila | J17: =J16/102*100 -> 693.13725 | K17: Computed - Less 2% margin from Merec to Aquila
B19: Production Depreciation MZN/MT | C19: 0 | D19: =C19/J4 -> 0 | E19: =C19*J3 -> 0 | F19: NA for Soybeans - No cleaning needed | H19: Price from Invictus to Customer | J19: =J20*102/100 -> 736.44 | K19: 1% sales commission & other cost
H20: Price from Aquila to Invictus | J20: 722 | K20: Provided by Invictus
B21: Electricity consumption per hour | C21: 0 | D21: 0 | E21: 0 | F21: 25 KW consumed per Hour - Non Applicable here | H21: Price from Merec to Aquila | J21: =J20/102*100 -> 707.84314 | K21: Computed - Less 2% margin from Merec to Aquila
B22: Unit Cost per KW | C22: 0 | D22: 0 | E22: 0 | F22: 10 MZN/KW - Non Applicable Here
B23: Machine Capacity per Hour | C23: 0 | D23: 0 | E23: 0 | F23: 2.5 MT per hour/20MT per Day - Non applicable here
B24: Electricity cost per MT/MZN | C24: =+IFERROR(C21*C22/C23,0) -> 0 | D24: =C24/J4 -> 0 | E24: =C24*J3 -> 0
B26: Machine Labour Rate per Day | C26: 0 | D26: 0 | E26: 0 | F26: Daily rate per worker - Non applicable here
B27: Labour Needs (workers/day) | C27: 0 | D27: 0 | E27: 0 | F27: Workers per day
B28: Machine hours per Day | C28: 0 | D28: 0 | E28: 0 | F28: Assumed 8hours - Mon applicable here
B29: MT Processed per Day | C29: 0 | D29: 0 | E29: 0 | F29: Capacity × hours of utilization
B30: Machine Labour Cost per MT | C30: =IFERROR(C26*C27/C29,0) -> 0 | D30: =+C30/J4 -> 0 | E30: =+C30*J3 -> 0
A32: Total Processing Cost - MZN/MT | C32: =+C17+C19+C24+C30 -> 116 | D32: =+D17+D19+D24+D30 -> 1.6338028 | E32: =+E17+E19+E24+E30 -> 232000
A34: PACKAGING COSTS+STACKING | B34: Sewing - Labour Rate | C34: =0.56*20 -> 11.2 | D34: =+C34/J4 -> 0.15774648 | E34: =+C34*$J$3 -> 22400 | F34: Charged per Shift/280MZN per shift - 280/500*20bags
B35: Labour requirement | C35: 1 | D35: 1 | E35: 1 | F35: 500 bags estimated per person
B36: Yarn (MZN/Roll) | C36: =1*20 -> 20 | D36: =+C36/J4 -> 0.28169014 | E36: =+C36*$J$3 -> 40000 | F36: Price per roll is 500 MZN- Assumed 500bags/roll - to be confimed with OPS - 500/500*20bags per MT
B37: Subtotal MZN/MT | C37: =+C34*C35+C36 -> 31.2 | D37: =+D34*D35+D36 -> 0.43943662 | E37: =+E34*E35+E36 -> 62400
B39: After Processing Stacking - Labour | C39: 0 | D39: =+C39/J4 -> 0 | E39: =+C39*J3 -> 0 | F39: Non applicable
B41: Packing - Labour | C41: 0 | D41: =+C41/J4 -> 0 | E41: =+C41*J3 -> 0 | F41: Non applicable
B42: Packaging Bags (High quality) | C42: =25.43*20 -> 508.6 | D42: =C42/$J$4 -> 7.1633803 | E42: =+C42*$J$3 -> 1017200 | F42: Current Purchasing price (25.43MZN per bag - Same as PP)
B43: Packaging Bags (Low quality) | C43: =12.93*20 -> 258.6 | D43: =C43/$J$4 -> 3.6422535 | E43: =+C43*$J$3 -> 517200 | F43: Current Purchasing price (12.93MZN per bag - Same as PP)
B44: Label - Material (Export req.) | C44: =5*20 -> 100 | D44: =C44/$J$4 -> 1.4084507 | E44: =+C44*$J$3 -> 200000 | F44: Stickers acceptable - 5MZN per label
A46: Total Packaging Cost MZN-MT | C46: =+SUM(C41:C44)+C37+C39 -> 898.4 | D46: =+SUM(D41:D44)+D37+D39 -> 12.653521 | E46: =+SUM(E41:E44)+E37+E39 -> 1796800
A48: AFTER PACK COSTS | B48: Drying - Labour | C48: 0 | D48: =+C48/$J$4 -> 0 | E48: =+C48*$J$3 -> 0
B49: Loading | C49: 29 | D49: =+C49/$J$4 -> 0.4084507 | E49: =+C49*$J$3 -> 58000
B50: Stuffing | C50: 29 | D50: =+C50/$J$4 -> 0.4084507 | E50: =+C50*$J$3 -> 58000
C51: =+SUM(C48:C50) -> 58 | D51: =+SUM(D48:D50) -> 0.81690141 | E51: =+SUM(E48:E50) -> 116000
A53: TOTAL EX FACTORY COST | C53: =+C11+C32+C46+C51 -> 38207.754 | D53: =+D11+D32+D46+D51 -> 532.90704 | E53: =+E11+E32+E46+E51 -> 75672800
A55: CUSTOMS & CLEARANCE | B55: Shore Handling | C55: =+'[4]Manica quot. 23MT'!F13*$J$4 -> 543.30435 | D55: =C55/$J$4 -> 7.6521739 | E55: =C55*$J$3 -> 1086608.7 | F55: Nacala Port Charges (Cfm)
B56: Port Weighbridge | C56: =+'[4]Manica quot. 23MT'!F14*$J$4 -> 95.695652 | D56: =C56/J4 -> 1.3478261 | E56: =C56*J3 -> 191391.3 | F56: Nacala Port Charges (Cfm)
B57: Delivery & Reception of Empty Container | C57: =+'[4]Manica quot. 23MT'!F15*$J$4 -> 46.304348 | D57: =C57/J4 -> 0.65217391 | E57: =C57*J3 -> 92608.696 | F57: Nacala Port Charges (Cfm)
B58: Agency Fee | C58: =+'[4]Manica quot. 23MT'!F23*$J$4 -> 463.04348 | D58: =C58/J4 -> 6.5217391 | E58: =C58*J3 -> 926086.96 | F58: Handling Charges (Manica)
B59: Scanning / Kudumba | C59: =+'[4]Manica quot. 23MT'!F26*$J$4 -> 185.21739 | D59: =C59/J4 -> 2.6086957 | E59: =C59*J3 -> 370434.78 | F59: Customs Clearance & Others
B60: Miscellaneous / Facilitation Fees | C60: =+'[4]Manica quot. 23MT'!F27*$J$4 -> 287.08696 | D60: =C60/J4 -> 4.0434783 | E60: =C60*J3 -> 574173.91 | F60: Customs Clearance & Others
B61: Tallying (incl. certificate) | C61: =+'[4]Manica quot. 23MT'!F28*$J$4 -> 92.608696 | D61: =C61/J4 -> 1.3043478 | E61: =C61*J3 -> 185217.39 | F61: Customs Clearance & Others
B62: Fumigation — estimate per certificate | C62: =+'[4]Manica quot. 23MT'!F29*$J$4 -> 108.04348 | D62: =C62/J4 -> 1.5217391 | E62: =C62*J3 -> 216086.96 | F62: Customs Clearance & Others
B63: Fetch Empty at Liner Depot → Shipper W/H → Port (Nacala city) | C63: =+'[4]Manica quot. 23MT'!F32*J4 -> 956.95652 | D63: =C63/$J$4 -> 13.478261 | E63: =C63*J3 -> 1913913 | F63: Transport Charges
B64: Subtotal Customs and Forwarding - Export Cargo | C64: =+SUM(C55:C63) -> 2778.2609 | D64: =+SUM(D55:D63) -> 39.130435 | E64: =+SUM(E55:E63) -> 5556521.7 | F64: 079/MFSN/CNF/EXPORT/PA/2025
B66: EXCLUDED CHARGES — Billed Per BL (10 Containers per BL)
B67: Export Documentation | C67: =+'[4]Manica quot. 23MT'!F35*$J$4 -> 54.021739 | D67: =C67/$J$4 -> 0.76086957 | E67: =C67*$J$3 -> 108043.48 | F67: Per BL ÷ C7 containers
B68: Customs Services Fee | C68: =+'[4]Manica quot. 23MT'!F36*$J$4 -> 3.7043478 | D68: =C68/$J$4 -> 0.052173913 | E68: =C68*$J$3 -> 7408.6957 | F68: Per BL ÷ C7 containers
B69: Customs Brokerage | C69: =+'[4]Manica quot. 23MT'!F37*$J$4 -> 61.73913 | D69: =C69/$J$4 -> 0.86956522 | E69: =C69*$J$3 -> 123478.26 | F69: Per BL ÷ C7 containers
B70: MCNet / Declaration (FOB >$50,000) | C70: =+'[4]Manica quot. 23MT'!F38*$J$4 -> 19.756522 | D70: =C70/$J$4 -> 0.27826087 | E70: =C70*$J$3 -> 39513.043 | F70: Per BL ÷ C7 containers
B71: Phytosanitary Certificate | C71: =+'[4]Manica quot. 23MT'!F39*$J$4 -> 24.695652 | D71: =C71/$J$4 -> 0.34782609 | E71: =C71*$J$3 -> 49391.304 | F71: Per BL ÷ C7 containers
B72: Phytosanitary Inspector Dislocation | C72: =+'[4]Manica quot. 23MT'!F40*$J$4 -> 15.434783 | D72: =C72/$J$4 -> 0.2173913 | E72: =C72*$J$3 -> 30869.565 | F72: Per BL ÷ C7 containers
B73: Certificate of Origin & LDC | C73: =+'[4]Manica quot. 23MT'!F41*$J$4 -> 24.695652 | D73: =C73/$J$4 -> 0.34782609 | E73: =C73*$J$3 -> 49391.304 | F73: Per BL ÷ C7 containers
B74: Sample Collection & Analysis (per lot) | C74: =4.10869565217391*$J$4 -> 291.71739 | D74: =C74/$J$4 -> 4.1086957 | E74: =C74*$J$3 -> 583434.78 | F74: ($945/lot)
B75: Craft Paper & Dry Bags ($75/container) | C75: =3.26086956521739*$J$4 -> 231.52174 | D75: =C75/$J$4 -> 3.2608696 | E75: =C75*$J$3 -> 463043.48 | F75: ($75 PER container)
B76: Subtotal Customs and Forwarding - Export Cargo | C76: =+SUM(C67:C75) -> 727.28696 | D76: =+SUM(D67:D75) -> 10.243478 | E76: =+SUM(E67:E75) -> 1454573.9
A78: Total Customs Cost- MZN/MT | C78: =+C76+C64 -> 3505.5478 | D78: =+D76+D64 -> 49.373913 | E78: =+E76+E64 -> 7011095.7 | F78: 079/MFSN/CNF/EXPORT/PA/2025
A80: FINANCE | B80: Finance Cost (14.75% p.a., 2.5-month cycle) | C80: =(C53)*J5 -> 1174.0924 | D80: =C80/J4 -> 16.536513 | E80: =C80*J3 -> 2348184.9 | F80: Applied on material cost
A81: CONTINGENCY | B81: Other Contingencies (5%) | C81: =((C32+C46+C100)*5%) -> 76.940954 | D81: =C81/J4 -> 1.0836754 | E81: =C81*J3 -> 153881.91 | F81: 5% of processing + customs + Opex of the total costs
A83: TOTAL FOB COST / MT | C83: =+C53+C78+SUM(C80:C81) -> 42964.335 | D83: =+D53+D78+D100+SUM(D80:D81) -> 607.28733 | E83: =+E53+E78+E100+SUM(E80:E81) -> 86234801
A85: FREIGHT COST | B85: Export Levy (2.5%) | C85: =+D85*J4 -> 976.25 | D85: =2.5/100*J8 -> 13.75 | E85: =C85*J3 -> 1952500 | F85: On Government declared price
B86: Stock Insurance (0.15% of FOB) | C86: =0.0015*C83 -> 64.446502 | D86: =D83*0.15% -> 0.91093099 | E86: =D86*J3*J4 -> 129352.2 | F86: Applied on USD FOB/MT
B87: Freight Cost | C87: =+D87*J4 -> 3408 | D87: 48 | E87: =D87*J4*J5 -> 104.725 | F87: Rate to India
A88: FREIGHT COST - MZN/MT | B88: Ocean Freight Cost | C88: =+SUM(C85:C87) -> 4448.6965 | D88: =+C88/J4 -> 62.657697 | E88: =+C88*J3 -> 8897393
A91: GROSS PROFIT MARGIN | B91: Total COGS/CFR Cost per MT | C91: =+C83+C88 -> 47413.031 | D91: =+C91/$J$4 -> 667.78917 | E91: =+C91*$J$3 -> 94826062 | F91: MT
B92: Total COGS/CFR Cost per bag | C92: =+C91/$C$111 -> 2370.6516 | D92: =+C92/$J$4 -> 33.389459 | E92: =+C92*$J$3 -> 4741303.1 | F92: Unit
B93: Gross Profit per MT | C93: =+($J$9*$J$4)-C91 -> 1799.7139 | D93: =+C93/$J$4 -> 25.348082 | E93: =+C93*$J$3 -> 3599427.7 | F93: Unit
B94: Gross Margin | C94: =+C93/(J9*J4) -> 0.036570077 | D94: =+D93/$J$9 -> 0.036570077 | E94: =+E93/(J9*J4*J3) -> 0.036570077 | F94: %
A96: OPEX | B96: Warehouse Costs | C96: =587958.241213763/J3 -> 293.97912 | D96: =C96/J4 -> 4.140551 | E96: =C96*J3 -> 587958.24 | F96: Allocation rate*cost/MT/Based on new warehouse rates
B97: Employment Costs | C97: =274219.405056139/J3 -> 137.1097 | D97: =C97/J4 -> 1.9311226 | E97: =C97*J3 -> 274219.41 | F97: Allocation rate*cost/MT
B98: Other General and Admin Costs | C98: =151715.356597734/J3 -> 75.857678 | D98: =C98/J4 -> 1.068418 | E98: =C98*J3 -> 151715.36 | F98: Allocation rate*cost/MT
B99: Depreciation | C99: =+(C117*C118+C117*D118+C117*E118+C117*F118)/J3 -> 17.472574 | D99: =C99/J4 -> 0.24609258 | E99: =C99*J3 -> 34945.147 | F99: Vehicle Depreciation*Allocation rate/MT
A100: Total OPEX MZN/MT | C100: =SUM(C96:C99) -> 524.41907 | D100: =SUM(D96:D99) -> 7.3861842 | E100: =SUM(E96:E99) -> 1048838.1
A102: NET PROFIT MARGIN | B102: Total Cost per MT | C102: =+C91+C100 -> 47937.45 | D102: =+C102/$J$4 -> 675.17536 | E102: =+C102*$J$3 -> 95874901 | F102: MT
B103: Total Cost per bag | C103: =+C102/C111 -> 2396.8725 | D103: =+C103/$J$4 -> 33.758768 | E103: =+C103*$J$3 -> 4793745 | F103: Unit
B104: Net Profit per MT | C104: =+($J$9*$J$4)-C102 -> 1275.2948 | D104: =+C104/$J$4 -> 17.961898 | E104: =+C104*$J$3 -> 2550589.6 | F104: Unit
B105: Net Margin | C105: =+C104/SUM($J$4*$J$9) -> 0.025913913 | D105: =+D104/J9 -> 0.025913913 | E105: =+E104/(J9*J4*J3) -> 0.025913913 | F105: %
B108: Weight Per Unit | C108: 50
B109: Number of Units (bags) | C109: =+C110/C108 -> 40000
B110: Total Weight in KG | C110: =+J3*1000 -> 2000000
B111: Units/MT | C111: =1000/C108 -> 20
A115: TOTAL CIF COST / MT (USD) | D115: =+D102 -> 675.17536
A117: SGA Depreciation (Per Month) | C117: 44375
C118: 0.33139083 | D118: 0.27054136 | E118: 0.14261829 | F118: 0.042945789
A121: COLOUR LEGEND
A122: Column C= Input data (update per purchase)
A123: Column D+E = Formula / calculated Columns
A124: Italic = Notes / source / confirmation needed

Sheet Sudan Pigeon Peas
C1: 46057
D2: PIGEON PEAS
D3: New Halfa | E3: Gadariff
B4: Purchase price | C4: SDG / MT | D4: ='[2]Input Sheet_'!K13 -> 2596153.8 | E4: ='[2]Input Sheet_'!K12 -> 2542857.1 | F4: updated
B5: Agent commission | C5: SDG / MT | D5: 20000 | E5: 25000 | F5: updated | I5: EX-rate | J5: ='[2]Input Sheet_'!E3 -> 3600
B6: Govt fee | C6: SDG / MT | D6: =212000-146330 -> 65670 | E6: 150000 | F6: updated | I6: Ave.RM bag weight | J6: 105
B7: Finance costs | C7: SDG / MT | D7: =SUM(D4:D6)*$J$7 -> 67045.596 | E7: =SUM(E4:E6)*$J$7 -> 67946.429 | F7: updated | I7: Finance cost % - 3 month holding | J7: ='[3]Inv Holding Period'!B14 -> 0.025 | K7: as per Inventory holding Period
B8: Supplier warehouse rent | C8: SDG / MT | D8: =$J$17/$J$25 -> 3000 | E8: 0 | F8: updated | H8: Waste | I8: Sifting Loss | J8: 0.05
B9: Quality Inspection | C9: SDG / MT | D9: =700*$J$11 -> 6666.6667 | E9: =700*$J$11 -> 6666.6667 | F9: updated | I9: Repacking Loss | J9: 0.005
B10: Zakat | C10: SDG / MT | D10: 0 | E10: 0 | F10: Included in PP | I10: Avg. Truck capacity(RM) | J10: 0 | K10: No cost related to RM truck
B11: Crops Market | C11: SDG / MT | D11: =((3500*20)+(12300/50)) -> 70246 | E11: 0 | F11: Included in PP for Gadariff | I11: No. of bags/MT | J11: =(1000/J6) -> 9.5238095
B12: State Tax | C12: SDG / MT | D12: =((3000*20)+(90000/50)) -> 61800 | E12: 0 | F12: Included in PP for Gadariff | I12: Ave. shipment QTY/MT | J12: 125 | K12: Hiba to confirm
B13: SSMO | C13: SDG / MT | D13: =(165000/50)+10420 -> 13720 | E13: 6193.75 | F13: updated | I13: Ex-form% | J13: 2e-05
B14: Other Govt fee | C14: SDG / MT | D14: =28200/50 -> 564 | E14: 0 | F14: updated | I14: Ave. capacity/container (20Ft) | J14: 25 | K14: Hiba to confirm
I15: No. of bags/MT (Packaging) | J15: =1000/50 -> 20 | K15: Hiba to confirm
B16: Total Material cost | D16: =SUM(D4:D14) -> 2904866.1 | E16: =SUM(E4:E14) -> 2798664 | I16: Avg. Truck capacity (FG) | J16: 25 | K16: Hiba to confirm
I17: Warehouse rent | J17: 600000
B18: Weighbridge | C18: SDG / MT | D18: 2000 | E18: =20000/50 -> 400 | F18: updated | I18: Bank Fees/EX Form | J18: 50000
B19: Offloading @ W/house | C19: SDG / MT | D19: 0 | E19: 0 | F19: Paid by Agent/Trader | I19: CBOS Pigeon Peas | J19: 375
B20: RM Shifting Cost | C20: SDG / MT | D20: =700*$J$11 -> 6666.6667 | E20: 0 | F20: No RM Shifting cost in Gadariff | I20: Ave. capacity/container (40Ft)
B21: Repackaging costs | C21: SDG / MT | D21: =1300*$J$11 -> 12380.952 | E21: =900*$J$15 -> 18000 | F21: updated | I21: Loading | J21: 16204.8
B22: Repackaging waste | C22: SDG / MT | D22: =SUM(D16:D21)/(1-$J$9)-SUM(D16:D21) -> 14703.084 | E22: =SUM(E16:E21)/(1-$J$9)-SUM(E16:E21) -> 14156.1 | F22: updated | J22: 2842.1053
B23: Packaging material cost | C23: SDG / MT | D23: =(0.23*J5*20)+(3000000/1500) -> 18560 | E23: =(0.23*J5*20)+(3500000/1500) -> 18893.333 | F23: updated | J23: 2857.0358
B24: Label | C24: SDG / MT | D24: =35*$J$15 -> 700 | E24: =35*$J$15 -> 700 | F24: updated | J24: =+J21+J22+J23 -> 21903.941
B25: Weighing & Sewing | C25: SDG / MT | D25: =(115*20)+(60000/50)+(25000/50) -> 4000 | E25: =(400*20)+(60000/100) -> 8600 | F25: updated | I25: Ave.purchase qty | J25: 200
B26: Stacking | C26: SDG / MT | D26: 0 | E26: 0 | F26: Included in Repacking cost | K26: For warehouse rent
B27: Loading | C27: SDG / MT | D27: 0 | E27: =400*20 -> 8000 | F27: Included in Repacking cost in Halfa
B28: Sale of Jute Bags | C28: SDG / MT | D28: =-3500*$J$11*85% -> -28333.333 | E28: =-3500*$J$11*85% -> -28333.333 | F28: updated
B30: Matrial cost Including Waste | C30: SDG / MT | D30: =SUM(D16:D29) -> 2935543.5 | E30: =SUM(E16:E29) -> 2839080.1
B32: LoadingTrucks to PZU | C32: SDG / MT | D32: 0 | E32: 0 | F32: Already done in material cost
B33: Transportation to PZU | C33: SDG / MT | D33: 65000 | E33: 70000 | F33: updated
B34: off loading at PZU | C34: SDG / MT | D34: =$J$24 -> 21903.941 | E34: =$J$24 -> 21903.941 | F34: updated
B35: W/hse rent at PZU | C35: SDG / MT | D35: 0 | E35: 0 | F35: Not added as shared warehouse
B36: Ex-factory | C36: SDG / MT | D36: =SUM(D32:D35) -> 86903.941 | E36: =SUM(E32:E35) -> 91903.941
B39: Ex- form issuance | C39: SDG / MT | D39: =$J$18/$J$12 -> 400 | E39: =$J$18/$J$12 -> 400 | F39: Updated
B40: Transportation of Container from Soba to Factory | C40: SDG / MT | D40: 0 | E40: 0
B41: Ex- form contract | C41: =0.002% -> 2e-05 | D41: =$J$13*$J$5*$J$19 -> 27 | E41: =$J$13*$J$5*$J$19 -> 27 | F41: Updated
B42: State Fees/Crop mkt fee/Taxes/SSMO | C42: SDG / MT | D42: 0 | E42: 0
B43: Weighing bridge PZU | C43: SDG / MT | D43: =15000/$J$16 -> 600 | E43: =15000/$J$16 -> 600 | F43: Updated
B44: Offloading to W/house (PZU) | C44: SDG / MT | D44: 0 | E44: 0
B45: Casual Labour (container inspection & stuffing) | C45: SDG / MT | D45: =27409*11*1/$J$12 -> 2411.992 | E45: =27409*11*1/$J$12 -> 2411.992 | F45: Updated
B46: Transportation of Container (from port to stuffing yard)round trip | C46: SDG / MT | D46: =(45000+150000)/($J$14) -> 7800 | E46: =(45000+150000)/($J$14) -> 7800 | F46: Updated
B47: Port admission fees (to acquired the container) | C47: SDG / MT | D47: =15219/($J$14) -> 608.76 | E47: =15219/($J$14) -> 608.76 | F47: Updated
B48: Casual Labour (Yard operations) | C48: SDG / MT | D48: 0 | E48: 0
B49: Loading Commodity towards Stuffing | C49: SDG / MT | D49: 0 | E49: 0
B50: Conitainer Lift on 20FT@ Port | C50: SDG / MT | D50: =(40000+170462.32)/$J$14 -> 8418.4928 | E50: =(40000+170462.32)/$J$14 -> 8418.4928 | F50: Updated
B51: Operation facilitation | C51: SDG / MT | D51: =30000/$J$12 -> 240 | E51: =30000/$J$12 -> 240 | F51: Updated
B52: Transportation from W/house to Yard | C52: SDG / MT | D52: 16000 | E52: 16000 | F52: Updated
B53: Loading Bags From WH ( if buyer tag using swing machine) (should add 15% VAT+17% TAX | C53: SDG / MT | D53: =(28280*1.17)*1.15 -> 38050.74 | E53: =(28280*1.17)*1.15 -> 38050.74 | F53: Updated
B54: Head of kalla @ wh for loading | C54: SDG / MT | D54: =((270000*1.17)*1.15)/$J$12 -> 2906.28 | E54: =((270000*1.17)*1.15)/$J$12 -> 2906.28 | F54: Updated
B55: Surveyor @ W/house / PF | C55: SDG / MT | D55: =20000/$J$12 -> 160 | E55: =20000/$J$12 -> 160 | F55: Updated
B56: Crane at Yard | C56: SDG / MT | D56: 0 | E56: 0
B57: Cleaning and Carton fixing | C57: SDG / MT | D57: 0 | E57: 0
B58: Forklift | C58: SDG / MT | D58: 0 | E58: 0
B59: Stuffing | C59: SDG / MT | D59: 0 | E59: 0
B60: Forest Fees-Storage cost | C60: SDG / MT | D60: 0 | E60: 0
B61: Transportation of Container | C61: SDG / MT | D61: 0 | E61: 0
B62: Transportation of Container to port (40ft)- Full Container | C62: SDG / MT | D62: 0 | E62: 0
B63: Containers Safty net | C63: SDG / MT | D63: 0 | E63: 0
B64: Stuffing Kalat | C64: SDG / MT | D64: =8100 -> 8100 | E64: =8100 -> 8100 | F64: Updated
B65: Open & Close Containers /Kalla | C65: SDG / MT | D65: =8000/$J$14 -> 320 | E65: =8000/$J$14 -> 320 | F65: Updated
B66: Head of kalla @Stuffing yard | C66: SDG / MT | D66: =200000/$J$12*2 -> 3200 | E66: =200000/$J$12*2 -> 3200 | F66: Updated
B67: Sealing cost | C67: SDG / MT | D67: =+(((0.6*(5+3))+45))*$J$5/$J$14 -> 7171.2 | E67: =+(((0.6*(5+3))+45))*$J$5/$J$14 -> 7171.2 | F67: Updated
B68: Local Charges | C68: SDG / MT | D68: =(54210+69261+7268+60355+6000+45857)/$J$14 -> 9718.04 | E68: =(54210+69261+7268+60355+6000+45857)/$J$14 -> 9718.04 | F68: Updated
B69: Arabic COO/ English COO/LDC Indian/ DFT Chainees | C69: SDG / MT | D69: 200 | E69: 200 | F69: Updated
B70: COO | C70: SDG / MT | D70: =20000/$J$12 -> 160 | E70: =20000/$J$12 -> 160 | F70: Updated
B71: Doc. private courier | C71: SDG / MT | D71: =230*$J$5/$J$12 -> 6624 | E71: =230*$J$5/$J$12 -> 6624 | F71: Updated
B72: Total Pre-Clearance | D72: =SUM(D39:D71) -> 113116.5 | E72: =SUM(E39:E71) -> 113116.5
B74: SPC | C74: SDG / MT | D74: =9200/3043.9*4001.45 -> 12094.136 | E74: =9200/3043.9*4001.45 -> 12094.136 | F74: Updated
B75: Custom forms | C75: SDG / MT | D75: 18265 | E75: 18265 | F75: Updated
B76: Plant Protection | C76: SDG / MT | D76: 300 | E76: =D76 -> 300 | F76: Updated
B77: SSMO | C77: SDG / MT | D77: 0 | E77: 0 | F77: Updated
B78: Health | C78: SDG / MT | D78: 34000 | E78: =D78 -> 34000 | F78: Updated
B79: Clearance Expenses | C79: SDG / MT | D79: 132.23 | E79: =D79 -> 132.23 | F79: Updated
B80: Total Clearance | C80: SDG / MT | D80: =SUM(D74:D79) -> 64791.366 | E80: =SUM(E74:E79) -> 64791.366
B82: Total FOB cost | C82: SDG / MT | D82: =SUM(D80,D72,D36,D30) -> 3200355.3 | E82: =SUM(E80,E72,E36,E30) -> 3108891.9
B84: Total FOB cost | C84: USD / MT | D84: =D82/$J$5 -> 888.98758 | E84: =E82/$J$5 -> 863.58108

Sheet Sorghum Sudan
B2: Component | C2: UOM | D2: SORGHUM
D3: Free Stock-Silos | E3: Purchase Outside Silos | F3: Processing Facility | H3: EX-rate (SDG/USD) | I3: ='[2]Input Sheet_'!E3 -> 3600
B4: Purchase Price | C4: SDG / MT | D4: =980000 -> 980000 | E4: ='[2]Output Sheet_'!D23 -> 1300000 | F4: =E4 -> 1300000 | H4: RM number of bags (MT) | I4: =1000/96 -> 10.416667
B5: Purchase agent commission | C5: SDG / MT | D5: 0 | E5: 15000 | F5: =E5 -> 15000 | H5: Finance cost % | I5: ='[5]Inv Holding Period'!B12 -> 0.025 | M5: Free stock | N5: Outside Silos | O5: Inside Silos
B6: Govt fees | C6: SDG / MT | E6: 0 | F6: =E6 -> 0 | H6: Waste | I6: 0.04 | K6: Loading to ABS Silos | L6: SDG/Bag | M6: =1000 -> 1000 | N6: =1000+300 -> 1300 | O6: =M6 -> 1000
B7: Finance Cost | C7: SDG / MT | D7: =SUM(D4:D5)*$I$5 -> 24500 | E7: =SUM(E4:E6)*$I$5 -> 32875 | F7: =SUM(F4:F6)*$I$5 -> 32875 | G7: Based on Inventory days holding.and Invictus annual interest rate | H7: Purchase Price (SDG/MT) | I7: 800000 | K7: Local shunting to ABS Silos | M7: =1200 -> 1200 | N7: =1300+200 -> 1500 | O7: =M7 -> 1200
B8: Quality Inspection | C8: SDG / MT | D8: ='[5]Siedahmed- 06012026'!D7 -> 1400 | E8: =400*$I$4 -> 4166.6667 | F8: =E8 -> 4166.6667 | H8: Agent Commission (SDG/MT) | I8: 10000 | K8: Weighbridge | M8: =5000/7 -> 714.28571 | N8: =5000/7 -> 714.28571 | O8: =5000/7 -> 714.28571
B9: Waste | C9: SDG / MT | D9: =(SUM(D4:D8,D11:D20,D26)/(1-$I$6))-SUM(D4:D8,D11:D20,D26) -> 46646.88 | E9: =(SUM(E4:E8,E11:E20,E26)/(1-$I$6))-SUM(E4:E8,E11:E20,E26) -> 60405.542 | F9: =(SUM(F4:F8,F11:F20,F26)/(1-$I$6))-SUM(F4:F8,F11:F20,F26) -> 62711.508 | K9: Offloading at ABS Silos | M9: 700 | N9: =800+300 -> 1100 | O9: =M9 -> 700
B10: Total Material Cost including waste | C10: SDG / MT | D10: =SUM(D4:D9) -> 1052546.9 | E10: =SUM(E4:E9) -> 1412447.2 | F10: =SUM(F4:F9) -> 1414753.2 | K10: ABS Silos receiving fees | M10: 468 | N10: =M10 -> 468 | O10: =M10 -> 468
B11: Loading to ABS Silos | C11: SDG / MT | D11: ='[5]Siedahmed- 06012026'!D10 -> 10416.667 | E11: =(1000+300)*$I$4 -> 13541.667 | F11: =(1000+300)*$I$4 -> 13541.667 | K11: Fumigation | M11: 4680 | N11: =M11 -> 4680 | O11: =N11 -> 4680
B12: Local shunting to ABS Silos | C12: SDG / MT | D12: ='[5]Siedahmed- 06012026'!D11 -> 12500 | E12: =(1300+200)*$I$4 -> 15625 | F12: =(1300+200)*$I$4 -> 15625 | K12: Storing | M12: 4680 | N12: 4680 | O12: 4680
B13: Weighbridge | C13: SDG / MT | D13: ='[5]Siedahmed- 06012026'!D12 -> 714.28571 | E13: =5000/7 -> 714.28571 | F13: =5000/7 -> 714.28571 | K13: Packaging | M13: =(0.23*I3*20.4)+(4000000/1500) -> 19557.867 | N13: =M13 -> 19557.867 | O13: =N13 -> 19557.867
B14: Offloading at ABS Silos/ Warehouse | C14: SDG / MT | D14: ='[5]Siedahmed- 06012026'!D13 -> 7291.6667 | E14: =(800+300)*$I$4 -> 11458.333 | F14: =(1000+300)*$I$4 -> 13541.667 | K14: Bags printing
B15: ABS Silos receiving fees | C15: SDG / MT | D15: ='[5]Siedahmed- 06012026'!D14 -> 4875 | E15: =585*$I$4 -> 6093.75 | F15: 0 | K15: Packing
B16: Fumigation | C16: SDG / MT | D16: ='[5]Siedahmed- 06012026'!D15 -> 14040 | E16: =7020*1 -> 7020 | F16: =3*$I$3 -> 10800 | K16: Loading
B17: Loading to PF | C17: SDG / MT | E17: 0 | F17: =(1000+300)*$I$4 -> 13541.667 | K17: Weighbridge
B18: Off Loading to PF | C18: SDG / MT | E18: 0 | F18: =(1000+300)*$I$4 -> 13541.667 | K18: Contingency
B19: Storing | C19: SDG / MT | D19: ='[5]Siedahmed- 06012026'!D16 -> 51480 | E19: =5850*3 -> 17550 | F19: 0
B20: Sifting | C20: SDG/MT | D20: ='[5]Siedahmed- 06012026'!D17 -> 5850 | E20: 7020 | F20: 55000
B21: Packaging | C21: SDG / MT | D21: ='[5]Siedahmed- 06012026'!D18 -> 19675.167 | E21: =(0.23*$I$3*20.4)+(4000000/1500) -> 19557.867 | F21: =E21 -> 19557.867
B22: Bags printing | C22: SDG / MT | D22: ='[5]Siedahmed- 06012026'!D19 -> 5350.1157 | E22: =(250*20.4)+(3500000/5000) -> 5800 | F22: =E22 -> 5800
B23: Packing | C23: SDG / MT | D23: ='[5]Siedahmed- 06012026'!D20 -> 12200 | E23: =(702+25)*20 -> 14540 | F23: 0
B24: Loading | C24: SDG / MT | D24: ='[5]Siedahmed- 06012026'!D21 -> 10000 | E24: =(300+200)*20 -> 10000 | F24: 0
B25: Weighbridge | C25: SDG / MT | D25: ='[5]Siedahmed- 06012026'!D22 -> 400 | E25: =20000/50 -> 400 | F25: =E25 -> 400
B26: Contingency | C26: SDG / MT | D26: ='[5]Siedahmed- 06012026'!D23 -> 6457.5 | E26: =SUM(E13,E15,E16,E19,E20,E23,E25)*0.35 -> 18668.312 | F26: =SUM(F13,F15,F16,F19,F20,F23,F25)*0.25 -> 16728.571
B27: Total Operational Expenses | C27: SDG / MT | D27: =SUM(D11:D26) -> 161250.4 | E27: =SUM(E11:E26) -> 147989.21 | F27: =SUM(F11:F26) -> 178792.39
B28: Crops markets (Transfer & Mobilization) | C28: SDG / MT | D28: ='[5]Siedahmed- 06012026'!D25 -> 24869.792 | E28: =2447.62*$I$4 -> 25496.042 | F28: =E28 -> 25496.042
B29: SSMO | C29: SDG/Shipment | D29: ='[5]Siedahmed- 06012026'!D26 -> 6800 | E29: =340*20 -> 6800 | F29: =E29 -> 6800
B30: Tax (State stamp) 50% | C30: SDG / MT | D30: ='[5]Siedahmed- 06012026'!D27 -> 2083.3333 | E30: =200*$I$4 -> 2083.3333 | F30: =E30 -> 2083.3333
B31: Other Taxes | C31: SDG / MT | E31: =1000*$I$4 -> 10416.667 | F31: =1000*$I$4 -> 10416.667
B32: Other Govt fees | C32: SDG / MT | E32: =2164*$I$4 -> 22541.667 | F32: =2164*$I$4 -> 22541.667
B33: Total Government Fees | C33: SDG / MT | D33: =SUM(D28:D30) -> 33753.125 | E33: =SUM(E28:E32) -> 67337.708 | F33: =SUM(F28:F32) -> 67337.708
B35: Total Cost SDG | C35: SDG / MT | D35: =D10+D27+D33 -> 1247550.4 | E35: =E10+E27+E33 -> 1627774.1 | F35: =F10+F27+F33 -> 1660883.3
B36: Total Cost USD | C36: USD / MT | D36: =D35/$I$3 -> 346.54178 | E36: =E35/$I$3 -> 452.15948 | F36: =F35/$I$3 -> 461.35646
B37: Expected Margins | D37: =D36*$C$37 -> 0 | E37: =E36*$C$37 -> 0 | F37: =F36*$C$37 -> 0
B38: Minimum Selling Price | D38: =SUM(D36:D37) -> 346.54178 | E38: =SUM(E36:E37) -> 452.15948 | F38: =SUM(F36:F37) -> 461.35646

Sheet Gum Arabic Sudan
C1: 46057
D2: Gum Arabic HASHAB | I2: Gum Arabic TALHA
D3: Without SD Processing | F3: SD Processing | I3: Without SD Processing | K3: SD Processing
D4: DRY | E4: FRESH | F4: DRY | G4: FRESH | I4: DRY | J4: FRESH | K4: DRY | L4: FRESH | T4: Fixed Monthly cost | U4: SDG /Month | V4: SDG/Year | W4: Assumption
B5: Purchase price | C5: SDG / MT | D5: ='[2]Input Sheet_'!K15 -> 13795000 | E5: ='[2]Input Sheet_'!K14 -> 12237500 | F5: =D5 -> 13795000 | G5: =E5 -> 12237500 | I5: ='[2]Input Sheet_'!K17 -> 3003750 | J5: ='[2]Input Sheet_'!K16 -> 1891250 | K5: =I5 -> 3003750 | L5: =(130000)*22.25 -> 2892500 | M5: Delivered to KRT
B6: Agent commission | C6: SDG / MT | D6: =7000*22.25 -> 155750 | E6: =7000*22.25 -> 155750 | F6: =7000*22.25 -> 155750 | G6: =7000*22.25 -> 155750 | I6: =1000*22.25 -> 22250 | J6: =1000*22.25 -> 22250 | K6: =1000*22.25 -> 22250 | L6: =1000*22.25 -> 22250 | M6: updated | O6: EX-rate | P6: ='[2]Input Sheet_'!E3 -> 3600 | T6: Warehouse Rent (SDG) | U6: =5000*$P$6 -> 18000000 | V6: =U6*12 -> 216000000
B7: Finance costs | C7: SDG / MT | D7: =$P$9*SUM(D5:D6) -> 348768.75 | E7: =$P$9*SUM(E5:E6) -> 309831.25 | F7: =$P$10*SUM(F5:F6) -> 465025 | G7: =$P$10*SUM(G5:G6) -> 413108.33 | I7: =$P$9*SUM(I5:I6) -> 75650 | J7: =$P$9*SUM(J5:J6) -> 47837.5 | K7: =$P$10*SUM(K5:K6) -> 100866.67 | L7: =$P$10*SUM(L5:L6) -> 97158.333 | M7: % From Inventory holding period | O7: Dry Hashab Monthly MC& S Capacity (MT) | P7: ='[3]Siedahmed 8-1-26'!H4 -> 160 | T7: Female Workers' Meals (SDG) | U7: 800000 | V7: =U7*9 -> 7200000 | W7: For 9 Months
B8: Govt fee | C8: SDG / MT | D8: 0 | E8: 0 | F8: 0 | G8: 0 | I8: 0 | J8: 0 | K8: 0 | L8: 0 | M8: Inclusive in Purchase Price | O8: Ave.Jute bag weight | P8: 100
B9: Zakat | C9: SDG / MT | D9: 0 | E9: 0 | F9: 0 | G9: 0 | I9: 0 | J9: 0 | K9: 0 | L9: 0 | O9: Finance cost % (Cleaned GA)- 3 month holding | P9: ='[3]Inv Holding Period'!B14 -> 0.025 | Q9: as per Inventory holding Period | T9: Female Workers' Supervision (SDG) | U9: 2720000 | V9: =U9*9 -> 24480000 | W9: For 9 Months
B10: Total Material cost | D10: =SUM(D5:D9) -> 14299519 | E10: =SUM(E5:E9) -> 12703081 | F10: =SUM(F5:F9) -> 14415775 | G10: =SUM(G5:G9) -> 12806358 | I10: =SUM(I5:I9) -> 3101650 | J10: =SUM(J5:J9) -> 1961337.5 | K10: =SUM(K5:K9) -> 3126866.7 | L10: =SUM(L5:L9) -> 3011908.3 | O10: Finance cost % (SD GA)- 4 month holding | P10: ='[3]Inv Holding Period'!B15 -> 0.033333333 | Q10: as per Inventory holding Period
O11: Manual cleaning waste | P11: 0.1 | T11: Total Fixed Cost (SDG) | U11: =SUM(U6:U9) -> 21520000 | V11: =SUM(V6:V9) -> 247680000
B12: Transportation (Obied to Baghir) | C12: SDG / MT | D12: 0 | E12: 0 | F12: 0 | G12: 0 | I12: 0 | J12: 0 | K12: 0 | L12: 0 | M12: Inclusive in Purchase Price | O12: Drying waste | P12: 0.1 | U12: HASHAB | W12: TALHA
B13: Weighbridge (Baghir) | C13: SDG / MT | D13: =55000/$P$20 -> 1100 | E13: =55000/$P$20 -> 1100 | F13: =55000/$P$20 -> 1100 | G13: =55000/$P$20 -> 1100 | I13: =55000/$P$20 -> 1100 | J13: =55000/$P$20 -> 1100 | K13: =55000/$P$20 -> 1100 | L13: =55000/$P$20 -> 1100 | M13: updated | O13: Kontar (Quintal) in 1 MT | P13: 22.25 | U13: Dry | V13: Fresh | W13: Dry | X13: Fresh
B14: Raw Offloading | C14: SDG / MT | D14: =2000*$P$21 -> 26000 | E14: =2000*$P$21 -> 26000 | F14: =2000*$P$21 -> 26000 | G14: =2000*$P$21 -> 26000 | I14: =2000*$P$21 -> 26000 | J14: =2000*$P$21 -> 26000 | K14: =2000*$P$21 -> 26000 | L14: =2000*$P$21 -> 26000 | M14: updated | N14: Waste | O14: DRY HASHAB MC & S Losses Inc by-products | P14: 0.15
B15: Raw Shifting | C15: SDG / MT | D15: =2000*$P$21 -> 26000 | E15: =2000*$P$21 -> 26000 | F15: =2000*$P$21 -> 26000 | G15: =2000*$P$21 -> 26000 | I15: =2000*$P$21 -> 26000 | J15: =2000*$P$21 -> 26000 | K15: =2000*$P$21 -> 26000 | L15: =2000*$P$21 -> 26000 | M15: updated | O15: FRESH HASHAB Drying, MC& S Losses Inc by-products | P15: 0.2
B16: Drying & Packing(Fresh) | C16: SDG / MT | D16: 0 | E16: =2000*$P$21 -> 26000 | F16: 0 | G16: =2000*$P$21 -> 26000 | I16: 0 | J16: =2000*$P$21 -> 26000 | K16: 0 | L16: =2000*$P$21 -> 26000 | M16: updated | O16: SD HASHAB losses | P16: 0.12
B17: Cost of Jute bags(Fresh) | C17: SDG / MT | D17: 0 | E17: =(4000*$P$21)/3 -> 17333.333 | F17: 0 | G17: =(4000*$P$21)/3 -> 17333.333 | I17: 0 | J17: =(4000*$P$21)/3 -> 17333.333 | K17: 0 | L17: =(4000*$P$21)/3 -> 17333.333 | M17: updated | O17: DRY TALHA MC & S Losses Inc by-products | P17: 0.1 | T17: Export Volumes(MT) | U17: =U25 -> 1232 | V17: 0 | W17: =W25 -> 952 | X17: 0
B18: Processing (Manual Cleaning & Sorting) | C18: SDG / MT | D18: =(3000*$P$21)+((7000*$P$21)*0.15) -> 52650 | E18: =(3000*$P$21)+((7000*$P$21)*0.15) -> 52650 | F18: =(3000*$P$21)+((7000*$P$21)*0.15) -> 52650 | G18: =(3000*$P$21)+((7000*$P$21)*0.15) -> 52650 | I18: =(3000*$P$21)+((7000*$P$21)*0.15) -> 52650 | J18: =(3000*$P$21)+((7000*$P$21)*0.15) -> 52650 | K18: =(3000*$P$21)+((7000*$P$21)*0.15) -> 52650 | L18: =(3000*$P$21)+((7000*$P$21)*0.15) -> 52650 | M18: updated | O18: FRESH TALHA Drying, MC& S Losses Inc by-products | P18: 0.13 | T18: Fixed cost -Total Export Volumes | U18: =$V$11/$X$25*$U$25 -> 1.3971692e+08 | V18: 0 | W18: =$V$11/$X$25*$W$25 -> 1.0796308e+08
B19: Moisture, Waste & By-product cost | C19: SDG / MT | D19: =SUM(D10,D12:D18)/(1-$P$14)-SUM(D10,D12:D18) -> 2542106.2 | E19: =SUM(E10,E12:E18)/(1-$P$15)-SUM(E10,E12:E18) -> 3213041.1 | F19: =SUM(F10,F12:F18)/(1-$P$14)-SUM(F10,F12:F18) -> 2562622.1 | G19: =SUM(G10,G12:G18)/(1-$P$15)-SUM(G10,G12:G18) -> 3238860.4 | I19: =SUM(I10,I12:I18)/(1-$P$17)-SUM(I10,I12:I18) -> 356377.78 | J19: =SUM(J10,J12:J18)/(1-$P$19)-SUM(J10,J12:J18) -> 287784.66 | K19: =SUM(K10,K12:K18)/(1-$P$17)-SUM(K10,K12:K18) -> 359179.63 | L19: =SUM(L10,L12:L18)/(1-$P$19)-SUM(L10,L12:L18) -> 431044.32 | O19: SD TALHA losses | P19: 0.12 | T19: Fixed cost -SDG/MT | U19: =U18/U17 -> 113406.59 | V19: =U19 -> 113406.59 | W19: =W18/W17 -> 113406.59 | X19: =W19 -> 113406.59
O20: Avg. Truck capacity(RM) | P20: 50 | T20: Fixed cost - USD/MT | U20: =U19/$P$6 -> 31.501832 | V20: =U20 -> 31.501832 | W20: =W19/$P$6 -> 31.501832 | X20: =W20 -> 31.501832
B21: Matrial cost including drying waste cost | C21: SDG / MT | D21: =SUM(D10:D19) -> 16947375 | E21: =SUM(E10:E19) -> 16065206 | F21: =SUM(F10:F19) -> 17084147 | G21: =SUM(G10:G19) -> 16194302 | I21: =SUM(I10:I19) -> 3563777.8 | J21: =SUM(J10:J19) -> 2398205.5 | K21: =SUM(K10:K19) -> 3591796.3 | L21: =SUM(L10:L19) -> 3592036 | O21: No. of bags/MT | P21: =ROUND(1000/77,0) -> 13
O22: Ave. shipment QTY/MT | P22: 100
B23: Fixed cost (W/H rent/Workers) | C23: SDG / MT | D23: =U19 -> 113406.59 | E23: =V19 -> 113406.59 | F23: =U19 -> 113406.59 | G23: =X19 -> 113406.59 | I23: =W19 -> 113406.59 | J23: =I23 -> 113406.59 | K23: =I23 -> 113406.59 | L23: =K23 -> 113406.59 | M23: W/H rent in USD and other W/H fixed charges | O23: Ex-form% | P23: 2e-05 | X23: Total
B24: Plastic bags (Packaging 50KG) | C24: SDG / MT | D24: =(0.23*$P$6*20)+(4500000/1500) -> 19560 | E24: =(0.23*$P$6*20)+(4500000/1500) -> 19560 | F24: =(0.23*$P$6*20)+(4500000/1500) -> 19560 | G24: =(0.23*$P$6*20)+(4500000/1500) -> 19560 | I24: =(0.23*$P$6*20)+(4500000/1500) -> 19560 | J24: =(0.23*$P$6*20)+(4500000/1500) -> 19560 | K24: =(0.23*$P$6*20)+(4500000/1500) -> 19560 | L24: =(0.23*$P$6*20)+(4500000/1500) -> 19560 | M24: Updated | O24: Ave. capacity/container (20Ft) | P24: =(800/40) -> 20 | T24: Export Volumes | U24: 1100 | W24: 850 | X24: =SUM(U24:W24) -> 1950
B25: Packaging of Processing output | C25: SDG / MT | D25: =(630+150)*$P$25 -> 15600 | E25: =(630+150)*$P$25 -> 15600 | F25: =(630+150)*$P$25 -> 15600 | G25: =(630+150)*$P$25 -> 15600 | I25: =(630+150)*$P$25 -> 15600 | J25: =(630+150)*$P$25 -> 15600 | K25: =(630+150)*$P$25 -> 15600 | L25: =(630+150)*$P$25 -> 15600 | M25: Updated | O25: No. of bags/MT (Packaging) | P25: =1000/50 -> 20 | T25: Extrapolated SD losses | U25: =(U24*(1+$P$16)) -> 1232 | W25: =(W24*(1+$P$19)) -> 952 | X25: =SUM(U25:W25) -> 2184
B26: Stacking of Processing output | C26: SDG / MT | D26: 0 | E26: 0 | F26: 0 | G26: 0 | I26: 0 | J26: 0 | K26: 0 | L26: 0 | M26: no information | O26: Avg. Truck capacity(Cleaned GA) | P26: 25
B27: By Product Sales | C27: SDG / MT | D27: =0.1*-4500000 -> -450000 | E27: =0.1*-4500000 -> -450000 | F27: =0.1*-4500000 -> -450000 | G27: =0.1*-4500000 -> -450000 | I27: =-0.07*(1000000) -> -70000 | J27: =-0.07*(1000000) -> -70000 | K27: =-0.07*(1000000) -> -70000 | L27: =-0.07*(1000000) -> -70000 | M27: Updated
B28: Ex-factory cost | C28: SDG / MT | D28: =SUM(D21,D23:D27) -> 16645942 | E28: =SUM(E21,E23:E27) -> 15763772 | F28: =SUM(F21,F23:F27) -> 16782714 | G28: =SUM(G21,G23:G27) -> 15892869 | I28: =SUM(I21,I23:I27) -> 3642344.4 | J28: =SUM(J21,J23:J27) -> 2476772.1 | K28: =SUM(K21,K23:K27) -> 3670362.9 | L28: =SUM(L21,L23:L27) -> 3670602.6 | M28: Updated | O28: Bank Fees/EX Form | P28: 50000
B29: LoadingTrucks to PZU | C29: SDG / MT | D29: =450*$P$25 -> 9000 | E29: =450*$P$25 -> 9000 | F29: 0 | G29: 0 | I29: =450*$P$25 -> 9000 | J29: =450*$P$25 -> 9000 | K29: 0 | L29: 0 | M29: Updated | O29: CBOS GA Hashab(SD) | P29: 3750
B30: Transportation to PZU | C30: SDG / MT | D30: 115000 | E30: =D30 -> 115000 | F30: 0 | G30: 0 | I30: 115000 | J30: =I30 -> 115000 | K30: 0 | L30: 0 | M30: Updated | O30: CBOS GA Hashab(Cleaned) | P30: 2200
B31: off loading at PZU | C31: SDG / MT | D31: 0 | E31: 0 | F31: 0 | G31: 0 | I31: 0 | J31: 0 | K31: 0 | L31: 0 | M31: Not required | O31: CBOS GA Talha (SD) | P31: 2000
B32: W/hse rent at PZU | C32: SDG / MT | D32: 0 | E32: 0 | F32: 0 | G32: 0 | I32: 0 | J32: 0 | K32: 0 | L32: 0 | M32: Not required | O32: CBOS GA Talha (Cleaned) | P32: 800
B33: Ex-factory | C33: SDG / MT | D33: =SUM(D28:D32) -> 16769942 | E33: =SUM(E28:E32) -> 15887772 | F33: =SUM(F28:F32) -> 16782714 | G33: =SUM(G28:G32) -> 15892869 | I33: =SUM(I28:I32) -> 3766344.4 | J33: =SUM(J28:J32) -> 2600772.1 | K33: =SUM(K28:K32) -> 3670362.9 | L33: =SUM(L28:L32) -> 3670602.6 | O33: Avg Shipment Qty/MT | P33: 100
O34: Avg Shipment Qty/MT (SD- HASHAB & TALHA) | P34: 40
O35: Ave. capacity/container (40Ft)
B36: Loading Trucks | C36: SDG / MT | D36: 0 | E36: 0 | F36: =450*$P$25 -> 9000 | G36: =450*$P$25 -> 9000 | I36: 0 | J36: 0 | K36: =450*$P$25 -> 9000 | L36: =450*$P$25 -> 9000 | M36: Updated | O36: Loading | P36: =16204.8*1.17 -> 18959.616
B37: local shunting to factory (Albagair to SD) | C37: SDG / MT | D37: 0 | E37: 0 | F37: =850000/$P$26 -> 34000 | G37: =850000/$P$26 -> 34000 | I37: 0 | J37: 0 | K37: =850000/$P$26 -> 34000 | L37: =850000/$P$26 -> 34000 | M37: Updated
B38: Weighbridge | C38: SDG / MT | D38: 0 | E38: 0 | F38: =55000/$P$26 -> 2200 | G38: =55000/$P$26 -> 2200 | I38: 0 | J38: 0 | K38: =55000/$P$26 -> 2200 | L38: =55000/$P$26 -> 2200 | M38: Updated | P38: =15%*SUM(P36+P37) -> 2843.9424
B39: Conversion cost (SD charges) | C39: USD / MT | D39: 0 | E39: 0 | F39: =809*$P$6 -> 2912400 | G39: =809*$P$6 -> 2912400 | I39: 0 | J39: 0 | K39: =809*$P$6 -> 2912400 | L39: =809*$P$6 -> 2912400 | M39: Updated | P39: =+P36+P37+P38 -> 21803.558
B40: SD Processing loss-Waste | C40: SDG / MT | D40: 0 | E40: 0 | F40: =SUM(F33,F36:F38)/(1-$P$16)-SUM(F33,F36:F38) -> 2294715.5 | G40: =SUM(G33,G36:G38)/(1-$P$16)-SUM(G33,G36:G38) -> 2173373 | I40: 0 | J40: 0 | K40: =SUM(K33,K36:K38)/(1-$P$19)-SUM(K33,K36:K38) -> 506667.67 | L40: =SUM(L33,L36:L38)/(1-$P$16)-SUM(L33,L36:L38) -> 506700.35 | M40: Updated
B41: Transportation (SD to PZU) | C41: SDG / MT | D41: 0 | E41: 0 | F41: =(115000*50)/20 -> 287500 | G41: =(115000*50)/20 -> 287500 | I41: 0 | J41: 0 | K41: =(115000*50)/20 -> 287500 | L41: =(115000*50)/20 -> 287500 | M41: Updated
B43: Ex-factory @ SD | C43: SDG / MT | D43: =SUM(D33:D41) -> 16769942 | E43: =SUM(E33:E41) -> 15887772 | F43: =SUM(F33:F41) -> 22322529 | G43: =SUM(G33:G41) -> 21311342 | I43: =SUM(I33:I41) -> 3766344.4 | J43: =SUM(J33:J41) -> 2600772.1 | K43: =SUM(K33:K41) -> 7422130.6 | L43: =SUM(L33:L41) -> 7422402.9
B46: Ex- form issuance | C46: SDG / MT | D46: =$P$28/$P$33 -> 500 | E46: =$P$28/$P$33 -> 500 | F46: =$P$28/$P$34 -> 1250 | G46: =$P$28/$P$34 -> 1250 | I46: =$P$28/$P$33 -> 500 | J46: =$P$28/$P$33 -> 500 | K46: =$P$28/$P$34 -> 1250 | L46: =$P$28/$P$34 -> 1250 | M46: Updated
B47: DHL fees -Sample 1 KG | C47: USD/MT | D47: 0 | E47: 0 | F47: =(23*$P$6)/$P$34 -> 2070 | G47: =(23*$P$6)/$P$34 -> 2070 | I47: 0 | J47: 0 | K47: =(23*$P$6)/$P$34 -> 2070 | L47: =(23*$P$6)/$P$34 -> 2070 | M47: Updated
B48: Phyto fees (estimated cost) | C48: USD/MT | D48: 0 | E48: 0 | F48: =(4*$P$6)/$P$24 -> 720 | G48: =(4*$P$6)/$P$24 -> 720 | I48: 0 | J48: 0 | K48: =(4*$P$6)/$P$24 -> 720 | L48: =(4*$P$6)/$P$24 -> 720 | M48: Updated
B49: Transportation of Container from Soba to Factory | C49: SDG / MT | F49: =850000/$P$24 -> 42500 | G49: =850000/$P$24 -> 42500 | K49: =850000/$P$24 -> 42500 | L49: =850000/$P$24 -> 42500 | M49: Updated
B50: Ex- form contract | C50: =0.002% -> 2e-05 | D50: =$P$30*$P$23*$P$6 -> 158.4 | E50: =$P$30*$P$23*$P$6 -> 158.4 | F50: =$P$29*$P$23*$P$6 -> 270 | G50: =$P$29*$P$23*$P$6 -> 270 | I50: =$P$32*$P$23*$P$6 -> 57.6 | J50: =$P$32*$P$23*$P$6 -> 57.6 | K50: =$P$31*$P$23*$P$6 -> 144 | L50: =$P$31*$P$23*$P$6 -> 144 | M50: Updated
B51: State Fees/Crop mkt fee/Taxes/SSMO | C51: SDG / MT | D51: 0 | E51: 0 | F51: 0 | G51: 0 | I51: 0 | J51: 0 | K51: 0 | L51: 0 | M51: Considered included in price
B52: Weighing bridge PZU | C52: SDG / MT | D52: =15000/$P$26 -> 600 | E52: =15000/$P$26 -> 600 | F52: =15000/$P$26 -> 600 | G52: =15000/$P$26 -> 600 | I52: =15000/$P$26 -> 600 | J52: =15000/$P$26 -> 600 | K52: =15000/$P$26 -> 600 | L52: =15000/$P$26 -> 600 | M52: Not there in Rasha's Details for SD
B53: Offloading to W/house (PZU) | C53: SDG / MT | D53: 0 | E53: 0 | F53: 0 | G53: 0 | I53: 0 | J53: 0 | K53: 0 | L53: 0 | M53: No Offloading in PZU
B54: Casual Labour (container inspection & stuffing) | C54: SDG / MT | D54: =27409*11*1/$P$33 -> 3014.99 | E54: =D54 -> 3014.99 | F54: 0 | G54: 0 | I54: =27409*11*1/$P$33 -> 3014.99 | J54: =I54 -> 3014.99 | K54: 0 | L54: 0 | M54: Updated
B55: Transportation of Container (from port to stuffing yard)round trip | C55: SDG / MT | D55: =(45000+150000)/($P$24) -> 9750 | E55: =(45000+150000)/($P$24) -> 9750 | F55: 0 | G55: 0 | I55: =(45000+150000)/($P$24) -> 9750 | J55: =(45000+150000)/($P$24) -> 9750 | K55: 0 | L55: 0 | M55: Updated
B56: Port admission fees (to acquired the container) | C56: SDG / MT | D56: =15219/($P$24) -> 760.95 | E56: =15219/($P$24) -> 760.95 | F56: 0 | G56: 0 | I56: =15219/($P$24) -> 760.95 | J56: =15219/($P$24) -> 760.95 | K56: 0 | L56: 0 | M56: Updated
B57: Casual Labour (Yard operations) | C57: SDG / MT | D57: 0 | E57: 0 | F57: 0 | G57: 0 | I57: 0 | J57: 0 | K57: 0 | L57: 0 | M57: not required
B58: Loading Commodity towards Stuffing | C58: SDG / MT | D58: 0 | E58: 0 | F58: 0 | G58: 0 | I58: 0 | J58: 0 | K58: 0 | L58: 0 | M58: not required
B59: Conitainer Lift on 20FT@ Port | C59: SDG / MT | D59: =(40000+170462.32)/$P$24 -> 10523.116 | E59: =(40000+170462.32)/$P$24 -> 10523.116 | F59: 0 | G59: 0 | I59: =(40000+170462.32)/$P$24 -> 10523.116 | J59: =(40000+170462.32)/$P$24 -> 10523.116 | K59: 0 | L59: 0 | M59: Updated
B60: Operation facilitation | C60: SDG / MT | D60: =30000/$P$33 -> 300 | E60: =30000/$P$33 -> 300 | F60: 0 | G60: 0 | I60: =30000/$P$33 -> 300 | J60: =30000/$P$33 -> 300 | K60: 0 | L60: 0 | M60: Updated
B61: Transportation from W/house to Yard | C61: SDG / MT | D61: 0 | E61: 0 | F61: 0 | G61: 0 | I61: 0 | J61: 0 | K61: 0 | L61: 0 | M61: This is not to be happening in GA. Direct transfer to Pzu
B62: Loading Bags From WH ( if buyer tag using swing machine) (should add 15% VAT+17% TAX | C62: SDG / MT | D62: 0 | E62: 0 | F62: 0 | G62: 0 | I62: 0 | J62: 0 | K62: 0 | L62: 0 | M62: No additional cost - already added up
B63: Head of kalla @ wh for loading | C63: SDG / MT | D63: =((270000*1.17)*1.15)/$P$33 -> 3632.85 | E63: =((270000*1.17)*1.15)/$P$33 -> 3632.85 | F63: 0 | G63: 0 | I63: =((270000*1.17)*1.15)/$P$33 -> 3632.85 | J63: =((270000*1.17)*1.15)/$P$33 -> 3632.85 | K63: 0 | L63: 0 | M63: Updated
B64: Surveyor @ W/house / PF | C64: SDG / MT | D64: =20000/$P$33 -> 200 | E64: =20000/$P$33 -> 200 | F64: 0 | G64: 0 | I64: =20000/$P$33 -> 200 | J64: =20000/$P$33 -> 200 | K64: 0 | L64: 0 | M64: Updated
B65: Crane at Yard | C65: SDG / MT | D65: 0 | E65: 0 | F65: =500000/$P$24 -> 25000 | G65: =500000/$P$24 -> 25000 | I65: 0 | J65: 0 | K65: =500000/$P$24 -> 25000 | L65: =500000/$P$24 -> 25000 | M65: Updated
B66: Cleaning and Carton fixing | C66: SDG / MT | D66: 0 | E66: 0 | F66: =230000/$P$24 -> 11500 | G66: =230000/$P$24 -> 11500 | I66: 0 | J66: 0 | K66: =230000/$P$24 -> 11500 | L66: =230000/$P$24 -> 11500 | M66: Updated
B67: Forklift | C67: SDG / MT | D67: 0 | E67: 0 | F67: =220000/$P$24 -> 11000 | G67: =220000/$P$24 -> 11000 | I67: 0 | J67: 0 | K67: =220000/$P$24 -> 11000 | L67: =220000/$P$24 -> 11000 | M67: Updated
B68: Stuffing | C68: SDG / MT | D68: 0 | E68: 0 | F68: 12000 | G68: 12000 | I68: 0 | J68: 0 | K68: 12000 | L68: 12000 | M68: Updated
B69: Forest Fees-Storage cost | C69: SDG / MT | D69: 0 | E69: 0 | F69: =3700*$P$13 -> 82325 | G69: =3700*$P$13 -> 82325 | I69: 0 | J69: 0 | K69: =3700*$P$13 -> 82325 | L69: =3700*$P$13 -> 82325 | M69: Updated
B70: Transportation of Container (from SD Factory to PZU ) | C70: SDG / MT | D70: 0 | E70: 0 | F70: =4025000/$P$24 -> 201250 | G70: =4025000/$P$24 -> 201250 | I70: 0 | J70: 0 | K70: =4025000/$P$24 -> 201250 | L70: =4025000/$P$24 -> 201250 | M70: Updated
B71: Transportation of Container to port (40ft)- Full Container | C71: SDG / MT | D71: 0 | E71: 0 | F71: =155000/$P$24 -> 7750 | G71: =155000/$P$24 -> 7750 | I71: 0 | J71: 0 | K71: =155000/$P$24 -> 7750 | L71: =155000/$P$24 -> 7750 | M71: Load will be 20 Tons
B72: Containers Safty net | D72: 0 | E72: 0 | F72: 0 | G72: 0 | I72: 0 | J72: 0 | K72: 0 | L72: 0 | M72: New requirement we don’t have cost Yet
B73: Stuffing Kalat | C73: SDG / MT | D73: =8100 -> 8100 | E73: =8100 -> 8100 | F73: 0 | G73: 0 | I73: =8100 -> 8100 | J73: =8100 -> 8100 | K73: 0 | L73: 0 | M73: Updated
B74: Open & Close Containers /Kalla | C74: SDG / MT | D74: =8000/$P$24 -> 400 | E74: =8000/$P$24 -> 400 | F74: =8000/$P$24 -> 400 | G74: =8000/$P$24 -> 400 | I74: =8000/$P$24 -> 400 | J74: =8000/$P$24 -> 400 | K74: =8000/$P$24 -> 400 | L74: =8000/$P$24 -> 400 | M74: Updated
B75: Head of kalla @Stuffing yard | C75: SDG / MT | D75: =200000/($P$33*1) -> 2000 | E75: =200000/($P$33*1) -> 2000 | F75: =200000/($P$34*1) -> 5000 | G75: =200000/($P$34*1) -> 5000 | I75: =200000/($P$33*1) -> 2000 | J75: =200000/($P$33*1) -> 2000 | K75: =200000/($P$34*1) -> 5000 | L75: =200000/($P$34*1) -> 5000 | M75: Updated
B76: Sealing cost | C76: SDG / MT | D76: =+(((0.6*(5+3))+45))*$P$6/$P$24 -> 8964 | E76: =+(((0.6*(5+3))+45))*$P$6/$P$24 -> 8964 | F76: 10000 | G76: =F76 -> 10000 | I76: =+(((0.6*(5+3))+45))*$P$6/$P$24 -> 8964 | J76: =+(((0.6*(5+3))+45))*$P$6/$P$24 -> 8964 | K76: 10000 | L76: =K76 -> 10000 | M76: Updated
B77: Local Charges | C77: SDG / MT | D77: =(54210+69261+7268+60355+6000+45857)/$P$24 -> 12147.55 | E77: =(54210+69261+7268+60355+6000+45857)/$P$24 -> 12147.55 | F77: =(54210+69261+7268+60355+6000+45857)/$P$24 -> 12147.55 | G77: =(54210+69261+7268+60355+6000+45857)/$P$24 -> 12147.55 | I77: =(54210+69261+7268+60355+6000+45857)/$P$24 -> 12147.55 | J77: =(54210+69261+7268+60355+6000+45857)/$P$24 -> 12147.55 | K77: =(54210+69261+7268+60355+6000+45857)/$P$24 -> 12147.55 | L77: =(54210+69261+7268+60355+6000+45857)/$P$24 -> 12147.55 | M77: Updated
B78: Arabic COO/ English COO/LDC Indian/ DFT Chainees | C78: SDG / MT | D78: 200 | E78: 200 | F78: 200 | G78: 200 | I78: 200 | J78: 200 | K78: 200 | L78: 200 | M78: Updated
B79: COO | C79: SDG / MT | D79: =20000/$P$33 -> 200 | E79: =20000/$P$33 -> 200 | F79: =20000/$P$34 -> 500 | G79: =20000/$P$34 -> 500 | I79: =20000/$P$33 -> 200 | J79: =20000/$P$33 -> 200 | K79: =20000/$P$34 -> 500 | L79: =20000/$P$34 -> 500 | M79: Updated
B80: Doc. private courier | C80: SDG / MT | D80: =230*$P$6/$P$33 -> 8280 | E80: =230*$P$6/$P$33 -> 8280 | F80: =230*$P$6/$P$34 -> 20700 | G80: =230*$P$6/$P$34 -> 20700 | I80: =230*$P$6/$P$33 -> 8280 | J80: =230*$P$6/$P$33 -> 8280 | K80: =230*$P$6/$P$34 -> 20700 | L80: =230*$P$6/$P$34 -> 20700 | M80: Updated
B81: Total Pre-Clearance | D81: =SUM(D46:D80) -> 69731.856 | E81: =SUM(E46:E80) -> 69731.856 | F81: =SUM(F46:F80) -> 447182.55 | G81: =SUM(G46:G80) -> 447182.55 | I81: =SUM(I46:I80) -> 69631.056 | J81: =SUM(J46:J80) -> 69631.056 | K81: =SUM(K46:K80) -> 447056.55 | L81: =SUM(L46:L80) -> 447056.55
B83: SPC | C83: SDG / MT | D83: =21954.8/3043.9*4001.45 -> 28861.341 | E83: =21954.8/3043.9*4001.45 -> 28861.341 | F83: =9200/3043.9*4001.45 -> 12094.136 | G83: =9200/3043.9*4001.45 -> 12094.136 | I83: =D83 -> 28861.341 | J83: =E83 -> 28861.341 | K83: =F83 -> 12094.136 | L83: =G83 -> 12094.136 | M83: Hiba/Rasha to confirm
B84: Custom forms | C84: SDG / MT | D84: 18265 | E84: 18265 | F84: =D84 -> 18265 | G84: =E84 -> 18265 | I84: 18265 | J84: 18265 | K84: =I84 -> 18265 | L84: =J84 -> 18265 | M84: Updated
B85: Plant Protection | C85: SDG / MT | D85: 3300 | E85: =D85 -> 3300 | F85: 300 | G85: 300 | I85: 3300 | J85: =I85 -> 3300 | K85: 300 | L85: 300 | M85: Updated
B86: SSMO | C86: SDG / MT | D86: 4510 | E86: =D86 -> 4510 | F86: =D86 -> 4510 | G86: =E86 -> 4510 | I86: 4510 | J86: =I86 -> 4510 | K86: =I86 -> 4510 | L86: =J86 -> 4510 | M86: Updated
B87: Health | C87: SDG / MT | D87: 0 | E87: =D87 -> 0 | F87: 12000 | G87: 12000 | I87: 0 | J87: =I87 -> 0 | K87: 12000 | L87: 12000 | M87: Not required for cleaned GA as per Clearance team
B88: Clearance Expenses | C88: SDG / MT | D88: 132.23 | E88: =D88 -> 132.23 | F88: =D88 -> 132.23 | G88: =E88 -> 132.23 | I88: 132.23 | J88: =I88 -> 132.23 | K88: =I88 -> 132.23 | L88: =J88 -> 132.23 | M88: Updated
B89: Total Clearance | C89: SDG / MT | D89: =SUM(D83:D88) -> 55068.571 | E89: =SUM(E83:E88) -> 55068.571 | F89: =SUM(F83:F88) -> 47301.366 | G89: =SUM(G83:G88) -> 47301.366 | I89: =SUM(I83:I88) -> 55068.571 | J89: =SUM(J83:J88) -> 55068.571 | K89: =SUM(K83:K88) -> 47301.366 | L89: =SUM(L83:L88) -> 47301.366 | M89: Updated
B91: Total FOB cost | C91: SDG / MT | D91: =SUM(D89,D81,D43) -> 16894742 | E91: =SUM(E89,E81,E43) -> 16012573 | F91: =SUM(F89,F81,F43) -> 22817013 | G91: =SUM(G89,G81,G43) -> 21805826 | I91: =SUM(I89,I81,I43) -> 3891044 | J91: =SUM(J89,J81,J43) -> 2725471.7 | K91: =SUM(K89,K81,K43) -> 7916488.5 | L91: =SUM(L89,L81,L43) -> 7916760.8
B93: Total FOB cost | C93: USD / MT | D93: =D91/$P$6 -> 4692.9839 | E93: =E91/$P$6 -> 4447.9369 | F93: =F91/$P$6 -> 6338.0592 | G93: =G91/$P$6 -> 6057.1738 | I93: =I91/$P$6 -> 1080.8456 | J93: =J91/$P$6 -> 757.07548 | K93: =K91/$P$6 -> 2199.0246 | L93: =L91/$P$6 -> 2199.1002

Sheet Chad Sesame
C1: USD' | D1: USD' | E1: FX | F1: 585
B2: Sesame Cost Sheet Forecast | C2: =$F$1 -> 585 | D2: =$F$1 -> 585
B3: Item Descriptions | C3: Ndjamena(mixed sesame) | D3: Ndjamena(Red Sesame) | E3: Moundou based processing (1) | F3: Value in $
B4: Purchase Price | C4: =110*5*1000 -> 550000 | D4: =105*5*1000 -> 525000 | E4: 510000 | F4: =E4/$F$1 -> 871.79487
B5: Commision for Agent | C5: 5000 | D5: 5000 | E5: 0 | F5: =E5/$F$1 -> 0
B6: Weighing, Handling & Local shunting (supplier/market to premises) | C6: =(225+100)*12.5 -> 4062.5 | D6: =(225+100)*12.5 -> 4062.5 | E6: 3750 | F6: =E6/$F$1 -> 6.4102564
B7: Quality Inspections Cost | C7: =67.5*12.5 -> 843.75 | D7: =67.5*12.5 -> 843.75 | E7: 1250 | F7: =E7/$F$1 -> 2.1367521
B8: Total Material Cost | C8: =SUM(C4:C7) -> 559906.25 | D8: =SUM(D4:D7) -> 534906.25 | E8: =SUM(E4:E7) -> 515000 | F8: =SUM(F4:F7) -> 880.34188
B9: Waste | C9: =(C8/(1-#REF!))-C8 -> #REF! | D9: =(D8/(1-#REF!))-D8 -> #REF! | E9: 50934.066 | F9: =E9/$F$1 -> 87.066779
B10: Handling & Local shunting (warehouse to processing facility) | E10: 0 | F10: =E10/$F$1 -> 0
B11: Sifting Cost | C11: 10326.98 | D11: 10326.98 | E11: 20000 | F11: =E11/$F$1 -> 34.188034
B12: Packaging material cost | C12: 5000 | D12: 5000 | E12: 5000 | F12: =E12/$F$1 -> 8.5470085
B13: Material Cost including waste | C13: =C8+C12+C9 -> #REF! | D13: =D8+D12+D9 -> #REF! | E13: =SUM(E8:E12) -> 590934.07 | F13: =SUM(F8:F12) -> 1010.1437
B14: Loading R.M from Mondou WH to Douala Processing facility | E14: 0 | F14: =E14/$F$1 -> 0
B15: Loading at Processing facility for trucking to Douala | C15: 2000 | D15: 2000 | E15: =1000 -> 1000 | F15: =E15/$F$1 -> 1.7094017
B16: Truck Treatment | E16: =500*5/27 -> 92.592593 | F16: =E16/$F$1 -> 0.15827794
B17: Loaded sesame quality inspection | E17: 0 | F17: =E17/$F$1 -> 0
B18: Loading Labor supervision | C18: =2500/27 -> 92.592593 | D18: =2500/27 -> 92.592593 | E18: 0 | F18: =E18/$F$1 -> 0
B19: Tags on the Bags | E19: =40*20 -> 800 | F19: =E19/$F$1 -> 1.3675214
B20: Ex-Facility cost | C20: =C13+#REF!+C15 -> #REF! | D20: =D13+#REF!+D15 -> #REF! | E20: =SUM(E13:E19) -> 592826.66 | F20: =SUM(F13:F19) -> 1013.3789
B21: Municipality fees | C21: 1630 | D21: 1630 | E21: 15000 | F21: =E21/$F$1 -> 25.641026
B22: Certificate of Origin( COO) fees | C22: 2000 | D22: 2000 | E22: 2000 | F22: =E22/$F$1 -> 3.4188034
B23: Clearance fees | C23: 4000 | D23: 4000 | E23: =15000/27 -> 555.55556 | F23: =E23/$F$1 -> 0.94966762
B24: Security, Police and ST | E24: =20000/27 -> 740.74074 | F24: =E24/$F$1 -> 1.2662235
B25: Boarder Gates | E25: =10000/27 -> 370.37037 | F25: =E25/$F$1 -> 0.63311174
B26: Customs - Facilities | C26: 4000 | D26: 4000 | E26: =30000/27 -> 1111.1111 | F26: =E26/$F$1 -> 1.8993352
B27: Phytosanitary - Health certificate Chad | C27: 370 | D27: 370 | E27: 316 | F27: =E27/$F$1 -> 0.54017094
B28: Customs - Export Duty | C28: 4000 | D28: 4000 | E28: 4000 | F28: =E28/$F$1 -> 6.8376068
B29: Contingency & Variance 5 % | C29: 1480 | D29: 1480 | E29: =E30*5% -> 2000 | F29: =E29/$F$1 -> 3.4188034
B30: Transportation from sifting facility to Douala | C30: 50000 | D30: 50000 | E30: =8000*5 -> 40000 | F30: =E30/$F$1 -> 68.376068
B31: Douala( Stuffing/Documentation/Clearance/fumigation etc) | C31: 30684.21 | D31: 30684.21 | E31: 32748.684 | F31: =E31/$F$1 -> 55.980657
B32: International Survoyor at loading port | C32: =50000/19 -> 2631.5789 | D32: =50000/19 -> 2631.5789 | E32: 3138.1579 | F32: =E32/$F$1 -> 5.3643725
B33: Lab Analysis Cost | E33: 1680.7974 | F33: =E33/$F$1 -> 2.8731579
B34: Warehouse Cost | E34: 4384.8 | F34: =E34/$F$1 -> 7.4953846
B35: Total Cost FOB | E35: =SUM(E20:E34) -> 700872.88 | F35: =SUM(F20:F34) -> 1198.0733
B36: Freight | E36: 19140 | F36: =E36/$F$1 -> 32.717949
B37: Broker's commission | E37: 7656 | F37: =E37/$F$1 -> 13.087179
B38: TOTAL CFR COST | E38: =SUM(E35:E37) -> 727668.88 | F38: =SUM(F35:F37) -> 1243.8784
B39: Market Price | E39: 765600 | F39: =E39/$F$1 -> 1308.7179
B40: Gross Margin | C40: =SUM(C20:C33) -> #REF! | D40: =SUM(D20:D33) -> #REF! | E40: =E39-E38 -> 37931.124 | F40: =F39-F38 -> 64.839529
B41: Gross Margin in % | E41: =E40/E39 -> 0.049544311 | F41: =F40/F39 -> 0.049544311
B42: Payroll | E42: 29648.347 | F42: =E42/$F$1 -> 50.680935
B43: Admin Cost | E43: 11008.8 | F43: =E43/$F$1 -> 18.818462
B44: Total Global Cost | C44: =SUM(C40:C40) -> #REF! | D44: =SUM(D40:D40) -> #REF! | E44: =E38+E42+E43 -> 768326.02 | F44: =F38+F42+F43 -> 1313.3778

Sheet Ethiopia Sesame
B2: Ethiopian Humera Sesame Seeds | W2: Bank rate | X2: =156 -> 156 | AB2: Black market | AC2: 185
B3: CBE rate | C3: ='[6]Cnt 1_114mt'!C3 -> 153.0847 | W3: Mkt rate | X3: 190 | AB3: Equiv FX | AC3: =L12 -> 194.71881
B4: Market Rate | C4: ='[6]Cnt 1_114mt'!C4 -> 153.0847 | I4: Volume (MT) | J4: =C10 -> 76 | W4: Average | X4: =AVERAGE(X2:X3) -> 173 | AB4: Diff | AC4: =(AC3-AC2)/AC2 -> 0.052534121
B5: Waste | C5: 0.05 | I5: Cost Elements | J5: Invictus | K5: Amros | L5: ALE
B6: Planned Volume | C6: ='[6]Finance costs'!I4 -> 3000 | I6: Purchase Cost | J6: =J11-SUM(J7:J10) -> 1096.2509 | K6: =E41 -> 1200 | L6: =E40-E15-E42 -> 1422.6123 | W6: 200000
I7: Freight | J7: =E44 -> 56.103751 | Z7: CBE
B8: White Humera Sesame (Buy/Clean-Addis) | E8: Mersin, Turkey | I8: Brokerage Fees | J8: =E42 -> 12.5 | K8: 0 | L8: 0 | W8: MOT | X8: 1700 | Y8: 200 | Z8: =X8*Y8 -> 340000 | AA8: 0.5 | AB8: 156 | AC8: =Z8*AB8 -> 53040000
I9: SBLC Finance costs | J9: =E15 -> 60.145313 | K9: 0 | L9: 0 | AB9: 190 | AC9: =Z8*AB9 -> 64600000
B10: Volume (MT) | C10: ='[6]FIFO '!M10 -> 76 | E10: Value Chain | I10: Margin | J10: =2%*J11 -> 25 | K10: =K11-K6 -> -103.74906 | L10: =L11-L6 -> -222.61232 | N10: Total Engineering Loss/MT | O10: =L10+K10 -> -326.36139
B11: Cost Component | C11: Birr/Quintal | D11: ETB/MT | E11: USD/MT | H11: =J10/J11 -> 0.02 | I11: Selling Price (Final customer) | J11: =E52 -> 1250 | K11: =J6 -> 1096.2509 | L11: =E41 -> 1200 | O11: =O10/1200 -> -0.27196782
B12: Purchase price ( at Actual Purchase FX) | C12: ='[6]FIFO '!N10 -> 18780.721 | D12: =C12*10 -> 187807.21 | E12: =D12/$C$4 -> 1226.819 | I12: Equivalent FX | L12: =((L6+(K10*-1))*C3)/L11 -> 194.71881
B13: Agent commission | C13: 100 | D13: =C13*10 -> 1000 | E13: =D13/$C$4 -> 6.5323314 | I13: Margin | J13: =(J11-SUM(J6:J9))/J11 -> 0.02 | K13: =(K11-SUM(K6:K9))/K11 -> -0.094639886 | L13: =(L11-SUM(L6:L9))/L11 -> -0.18551027
B14: Finance costs Local facility | C14: =SUM(C12:C13)*'[6]Finance costs'!$C$6 -> 625.42389 | D14: =C14*10 -> 6254.2389 | E14: =D14/$C$4 -> 40.854762
B15: SBLC Finance costs | C15: =D15/10 -> 920.73271 | D15: =E15*$C$3 -> 9207.3271 | E15: ='[6]Finance costs'!C12+'[6]Finance costs'!C16 -> 60.145313 | I15: Cost of ALE | L15: =L6 -> 1422.6123
B16: Loading at sourcing point | D16: =C16*10 -> 0 | E16: =D16/$C$4 -> 0 | I16: Margin in AMROS | L16: =-K10 -> 103.74906
B17: Off loading at cleaning facility | D17: =C17*10 -> 0 | E17: =D17/$C$4 -> 0
B18: Taxation & Crops Markets | D18: =C18*10 -> 0 | E18: =D18/$C$4 -> 0 | I18: Total cost to be absorbed | L18: =L15+L16 -> 1526.3614
B19: Quality Inspection | C19: 20 | D19: =C19*10 -> 200 | E19: =D19/$C$4 -> 1.3064663 | I19: Equivalent in ETB | L19: =L18*C3 -> 233662.57 | AB19: ALE will Sell to AMROS at MOT price | AC19: =L11 -> 1200
B20: Material Cost | C20: =SUM(C12:C19) -> 20446.878 | D20: =SUM(D12:D19) -> 204468.78 | E20: =SUM(E12:E19) -> 1335.6578 | I20: FX Equiv of rate for MOT received | L20: =L19/L11 -> 194.71881
B21: Shifting | D21: =C21*10 -> 0 | E21: =D21/$C$4 -> 0
B22: Sifting Cost | C22: 175 | D22: =C22*10 -> 1750 | E22: =D22/$C$4 -> 11.43158
B23: Waste % | C23: =SUM(C20:C22)/(1-$C$5)-SUM(C20:C22) -> 1085.362 | D23: =C23*10 -> 10853.62 | E23: =D23/$C$4 -> 70.899443
B24: Labour & Operations costs | D24: =C24*10 -> 0 | E24: =D24/$C$4 -> 0
B25: Warehousing costs | D25: =C25*10 -> 0 | E25: =D25/$C$4 -> 0
B26: Fumigation Charges | C26: 53 | D26: =C26*10 -> 530 | E26: =D26/$C$4 -> 3.4621357
B27: Material Cost including waste | C27: =SUM(C20:C26) -> 21760.24 | D27: =SUM(D20:D26) -> 217602.4 | E27: =SUM(E20:E26) -> 1421.451
B28: Packaging material cost | C28: 78 | D28: =C28*10 -> 780 | E28: =D28/$C$4 -> 5.0952185
B29: Weighbridge (at Facility) | C29: 0 | D29: =C29*10 -> 0 | E29: =D29/$C$4 -> 0
B30: Loading | D30: =C30*10 -> 0 | E30: =D30/$C$4 -> 0
B31: Local Surveyor costs | C31: 24 | D31: =C31*10 -> 240 | E31: =D31/$C$4 -> 1.5677595
B32: Warehousing costs | D32: =C32*10 -> 0 | E32: =D32/$C$4 -> 0 | I32: OPEX?
B33: Ex-factory | C33: =SUM(C27:C32) -> 21862.24 | D33: =SUM(D27:D32) -> 218622.4 | E33: =SUM(E27:E32) -> 1428.114 | I33: House rent?
B34: Insurance (0.1% of ex factory) | C34: =0.1%*C33 -> 21.86224 | D34: =C34*10 -> 218.6224 | E34: =D34/$C$4 -> 1.428114 | I34: Allowances?
B35: Documents | C35: 17 | D35: =C35*10 -> 170 | E35: =D35/$C$4 -> 1.1104963
B36: Transport | C36: 550 | D36: =C36*10 -> 5500 | E36: =D36/$C$4 -> 35.927823
B37: Clearance Cost | C37: 22 | D37: =C37*10 -> 220 | E37: =D37/$C$4 -> 1.4371129
B38: Djibouti Transit Cost | C38: =D38/10 -> 362.50457 | D38: =E38*C4 -> 3625.0457 | E38: 23.68
B39: Shipping line Local Charges | C39: 54.5 | D39: =C39*10 -> 545 | E39: =D39/$C$4 -> 3.5601206
B40: FOB | C40: =SUM(C33:C39) -> 22890.107 | D40: =SUM(D33:D39) -> 228901.07 | E40: =SUM(E33:E39) -> 1495.2576
B41: MOT Price | C41: =D41/100 -> 1837.0164 | D41: =E41*$C$3 -> 183701.64 | E41: 1200
B42: Brokerage | C42: =D42/100 -> 19.135587 | D42: =E42*$C$3 -> 1913.5587 | E42: =1%*E52 -> 12.5
B44: Sea Freight | E44: =[6]Freight!N62 -> 56.103751
B45: CIF costs | C45: =C40+C44 -> 22890.107 | D45: =D40+D44 -> 228901.07 | E45: =E40+E44 -> 1551.3614
B47: MOT Price | E47: 1200 | G47: ok
B48: Gross Margin/MT at MOT Price | E48: =E47-E45 -> -351.36139
B49: GM % at MOT price in ALE | E49: =E48/E47 -> -0.29280116
B52: Final customer prices | E52: =[6]Contracts!D28 -> 1250 | F52: CFR to Turkey
B53: Gross Margin/MT at Final Customer Price | E53: =E52-E45 -> -301.36139
B54: GM % at Final Customer price at Value Chain | E54: =E53/E52 -> -0.24108911

Sheet Manica quotation
A1: CFS EXPORT COST SHEET — GREEN MUNG (NACALA, 2026)
A2: Manica Freight Services | Container: 20'GP | Commodity: Green Mung | Ref: 079/MFSN/CNF/EXPORT/PA/2025 | Date: April 22, 2026
A4: SHIPMENT ASSUMPTIONS (Blue cells = inputs you can change)
B5: Total Volume (MT) | C5: 2000 | D5: MT | E5: Total volume to be purchased
B6: Load per Container (MT) | C6: 19 | D6: MT | E6: MT per container
B7: Number of Containers | C7: 80 | D7: auto | E7: Total Containers for 2000MR
B8: Number of BLs | C8: 16 | E8: Assumed
B9: ICM Tax Rate (Green Mung) | C9: 5 | D9: USD/MT | E9: To be expensed
A11: # | B11: Charge Description | C11: Unit Rate (USD) | D11: Basis | E11: Per Container (20'GP) | F11: Per MT (÷19) | G11: Full Shipment (×5 containers) | H11: 19
A12: 1. NACALA PORT CHARGES (CFM)
A13: 1 | B13: Shore Handling | C13: 176 | D13: Per container | E13: =+C13 -> 176 | F13: =E13/C6 -> 9.2631579 | G13: =E13*C7 -> 14080
A14: 2 | B14: Port Weighbridge | C14: 31 | D14: Per container | E14: =+C14 -> 31 | F14: =E14/C6 -> 1.6315789 | G14: =E14*C7 -> 2480
A15: 3 | B15: Delivery & Reception of Empty Container | C15: 15 | D15: Per container | E15: =+C15 -> 15 | F15: =E15/C6 -> 0.78947368 | G15: =E15*C7 -> 1200
A16: Sub-Total — Port Charges | E16: =SUM(E13:E15) -> 222 | F16: =E16/C6 -> 11.684211 | G16: =E16*C7 -> 17760
A17: 2. SHIPPING LINE CHARGES (MSC)
A18: 4 | B18: Terminal Handling (THC) | C18: 140 | D18: Per container | E18: =+C18 -> 140 | F18: =E18/C6 -> 7.3684211 | G18: =E18*C7 -> 11200
A19: 5 | B19: Seal | C19: 10 | D19: Per container | E19: =+C19 -> 10 | F19: =E19/C6 -> 0.52631579 | G19: =E19*C7 -> 800
A20: 6 | B20: Container Release (Lift On Fee) | C20: 65 | D20: Per container | E20: =+C20 -> 65 | F20: =E20/C6 -> 3.4210526 | G20: =E20*C7 -> 5200
A21: Sub-Total — Shipping Line | E21: =SUM(E18:E20) -> 215 | F21: =E21/C6 -> 11.315789 | G21: =E21*C7 -> 17200
A22: 3. HANDLING CHARGES (MANICA)
A23: 7 | B23: Agency Fee | C23: 100 | D23: Per container | E23: =+C23 -> 100 | F23: =E23/C6 -> 5.2631579 | G23: =E23*C7 -> 8000
A24: Sub-Total — Handling | E24: =E23 -> 100 | F24: =E24/C6 -> 5.2631579 | G24: =E24*C7 -> 8000
A25: 4. CUSTOMS CLEARANCE & OTHERS
A26: 8 | B26: Scanning / Kudumba | C26: 60 | D26: Per container | E26: =+C26 -> 60 | F26: =E26/C6 -> 3.1578947 | G26: =E26*C7 -> 4800
A27: 9 | B27: Miscellaneous / Facilitation Fees | C27: 93 | D27: Per container | E27: =+C27 -> 93 | F27: =E27/C6 -> 4.8947368 | G27: =E27*C7 -> 7440
A28: 10 | B28: Tallying (incl. certificate) | C28: 30 | D28: Per container | E28: =+C28 -> 30 | F28: =E28/C6 -> 1.5789474 | G28: =E28*C7 -> 2400
A29: 11 | B29: Fumigation — estimate per certificate | C29: 35 | D29: Per container | E29: =+C29 -> 35 | F29: =E29/C6 -> 1.8421053 | G29: =E29*C7 -> 2800
A30: Sub-Total — Customs | E30: =SUM(E26:E29) -> 218 | F30: =E30/C6 -> 11.473684 | G30: =E30*C7 -> 17440
A31: 5. TRANSPORT CHARGES
A32: 12 | B32: Fetch Empty at Liner Depot → Shipper W/H → Port (Nacala city) | C32: 240 | D32: Per container | E32: =+C32 -> 240 | F32: =E32/C6 -> 12.631579 | G32: =E32*C7 -> 19200
A33: Sub-Total — Transport | E33: =E32 -> 240 | F33: =E33/C6 -> 12.631579 | G33: =E33*C7 -> 19200
A34: 6. EXCLUDED CHARGES — Billed Per BL (Spread across 5containers per BL) | E34: Per BL (Each BL 10 containers 20'GP) | F34: Per MT (÷19) | G34: Full Cost
A35: 13 | B35: Export Documentation | C35: 175 | D35: Per BL ÷ C7 containers | E35: =+C35/10 -> 17.5 | F35: =+E35/$C$6 -> 0.92105263 | G35: =C35 -> 175 | H35: 1BL = 10 CONTAINERS
A36: 14 | B36: Customs Services Fee | C36: 12 | D36: Per BL ÷ C7 containers | E36: =+C36/10 -> 1.2 | F36: =+E36/$C$6 -> 0.063157895 | G36: =C36 -> 12 | H36: =+C35/125 -> 1.4
A37: 15 | B37: Customs Brokerage | C37: 200 | D37: Per BL ÷ C7 containers | E37: =+C37/10 -> 20 | F37: =+E37/$C$6 -> 1.0526316 | G37: =C37 -> 200
A38: 16 | B38: MCNet / Declaration (FOB >$50,000) | C38: 64 | D38: Per BL ÷ C7 containers | E38: =+C38/10 -> 6.4 | F38: =+E38/$C$6 -> 0.33684211 | G38: =C38 -> 64
A39: 17 | B39: Phytosanitary Certificate | C39: 80 | D39: Per BL ÷ C7 containers | E39: =+C39/10 -> 8 | F39: =+E39/$C$6 -> 0.42105263 | G39: =C39 -> 80
A40: 18 | B40: Phytosanitary Inspector Dislocation | C40: 50 | D40: Per BL ÷ C7 containers | E40: =+C40/10 -> 5 | F40: =+E40/$C$6 -> 0.26315789 | G40: =C40 -> 50
A41: 19 | B41: Certificate of Origin & LDC | C41: 80 | D41: Per BL ÷ C7 containers | E41: =+C41/10 -> 8 | F41: =+E41/$C$6 -> 0.42105263 | G41: =C41 -> 80
A42: Sub-Total — Excluded (Per BL) Charges | E42: =E35+E36+E37+E38+E39+E40+E41 -> 66.1 | F42: =E42/C6 -> 3.4789474 | G42: =G35+G36+G37+G38+G39+G40+G41 -> 661
A43: 7. ICM TAX — Green Mung Specific
A44: 20 | B44: ICM Tax @ $5.00/MT (applied to full tonnage) | C44: =C9 -> 5 | D44: Per MT × 25 MT/container | E44: =C9*C6 -> 95 | F44: =C9 -> 5 | G44: =C9*C5 -> 10000
A46: COST SUMMARY
A47: CFS Fixed Charges (Manica Quoted) | E47: =E16+E21+E24+E30+E33 -> 995 | F47: =E47/C6 -> 52.368421 | G47: =E47*C7 -> 79600
A48: Excluded Charges (Per BL, spread) | E48: =E42 -> 66.1 | F48: =E48/C6 -> 3.4789474 | G48: =G42 -> 661
A49: ICM Tax (Green Mung @ $5/MT) | E49: =E44 -> 95 | F49: =E49/C6 -> 5 | G49: =G44 -> 10000
A50: TOTAL COST PER CONTAINER | PER MT | FULL SHIPMENT | E50: =E47+E48+E49 -> 1156.1 | F50: =E50/C6 -> 60.847368 | G50: =SUM(G47:G49) -> 90261
A52: NOTES & EXCLUSIONS
A53: ⚠ Sea freight (Nacala → destination port) is NOT included — to be agreed with shipping line (MSC or other).
A54: ⚠ Marine cargo insurance, police/customs escort, and lift-on/off at shipper yard are excluded.
A55: ⚠ Sample Collection & Analysis ($945/lot) excluded — charged once per shipment at cost.
A56: ⚠ Craft Paper & Dry Bags ($75/container) excluded — subject to availability.
A57: ⚠ Variable at-cost charges (port storage, liner detention, TEEN storage, truck demurrage) not included.
A58: ℹ Payment strictly upfront. Disbursement fee of 5% applies on unpaid advance amounts.
A59: ℹ Documents must be submitted to Manica office at least 15 working days before vessel arrival.
A60: ℹ Quotation valid 30 days from April 22, 2026. All third-party rates subject to change.
A61: ℹ Source: Manica Freight Services Mozambique, Ref 079/MFSN/CNF/EXPORT/PA/2025, April 22, 2026.

Sheet 1. OPEX Inputs
B2: Fiscal Year: | D2: 2025/2026
B3: Currency: | D3: MZN
B6: Cost Item | C6: Type | D6: December | E6: January | F6: Februay | G6: Total (MZN) | H6: Average | I6: Notes
B7: Warehouse Overhead
B8: Nacala Warehouse rent | C8: Fixed | D8: 390000 | E8: 390000 | F8: 390000 | G8: =+SUM(D8:F8) -> 1170000 | H8: =125000*4 -> 500000
B9: Warehouse Electricity & Water | C9: Fixed | D9: 12420 | E9: 23340 | F9: 19900 | G9: =+SUM(D9:F9) -> 55660 | H9: =+AVERAGE(D9:F9) -> 18553.333
B10: Warehouse Cleaning Charges | C10: Fixed | D10: =+AVERAGE(E10:F10) -> 34442.875 | E10: 32450 | F10: 36435.75 | G10: =+SUM(D10:F10) -> 103328.62 | H10: =+AVERAGE(D10:F10) -> 34442.875
B11: Warehouse Maintenance charges | C11: Variable | D11: 1500 | E11: 1500 | F11: 1500 | G11: =+SUM(D11:F11) -> 4500 | H11: =+AVERAGE(D11:F11) -> 1500 | I11: To Confirm, only around 1500 booked in March
B12: Warehouse staff Salary | C12: Fixed | D12: 121475.53 | E12: 124418.82 | F12: 114811.3 | G12: =+SUM(D12:F12) -> 360705.65 | H12: =+AVERAGE(D12:F12) -> 120235.22 | I12: Warehouse+quality control employment COGS
B13: Subtotal | D13: =+SUM(D8:D12) -> 559838.41 | E13: =+SUM(E8:E12) -> 571708.82 | F13: =+SUM(F8:F12) -> 562647.05 | G13: =+SUM(D13:F13) -> 1694194.3 | H13: =+SUM(H8:H12) -> 674731.42
B14: Employee Overhead
B15: Employee Salary(Export Staff) | C15: Fixed | D15: =400*3*63.89 -> 76668 | E15: =400*3*63.89 -> 76668 | F15: =400*3*63.89 -> 76668 | G15: =+SUM(D15:F15) -> 230004 | H15: =+AVERAGE(D15:F15) -> 76668 | I15: Staff hire from India (3 persons)@$ 400/-per person/per month
B16: Employee house rent | C16: Fixed | D16: 105000 | E16: 105000 | F16: 105000 | G16: =+SUM(D16:F16) -> 315000 | H16: =+AVERAGE(D16:F16) -> 105000 | I16: Average cost
B17: Employee utility expenses | C17: Fixed | D17: 16225 | E17: 10200 | F17: 32725 | G17: =+SUM(D17:F17) -> 59150 | H17: =+AVERAGE(D17:F17) -> 19716.667 | I17: (Electricity/Gas/DSTV entertainment)
B18: Employee communication expenses | C18: Fixed | D18: 5300 | E18: 0 | F18: 4600 | G18: =+SUM(D18:F18) -> 9900 | H18: =+AVERAGE(D18:F18) -> 3300
B19: Employee food expenses | C19: Fixed | D19: 32480 | E19: 76800 | F19: 34987 | G19: =+SUM(D19:F19) -> 144267 | H19: =+AVERAGE(D19:F19) -> 48089 | I19: (Hired staff from overseas)
B20: Employee conveyance expenses | C20: Fixed | D20: 19069 | E20: 4650 | F20: 25930 | G20: =+SUM(D20:F20) -> 49649 | H20: =+AVERAGE(D20:F20) -> 16549.667 | I20: (Fuel/driver/average/proportionate car maintenance as logistic charges)
B21: Subtotal | D21: =+SUM(D15:D20) -> 254742 | E21: =+SUM(E15:E20) -> 273318 | F21: =+SUM(F15:F20) -> 279910 | G21: =+SUM(D21:F21) -> 807970 | H21: =+SUM(H15:H20) -> 269323.33
B22: Head office/branch office /Overhead expenses | C22: Fixed | G22: =+SUM(D22:F22) -> 0 | I22: Proportionate HO/branch overhead charges
B23: TOTAL MONTHLY FIXED COST | D23: =+D13+D21+D22 -> 814580.41 | E23: =+E13+E21+E22 -> 845026.82 | F23: =+F13+F21+F22 -> 842557.05 | G23: =D23*12 -> 9774964.9 | H23: =+H21+H13 -> 944054.76
H24: =+SUM(H16:H20) -> 192655.33
